{
  "major": "Biology, B.S.",
  "from": {
    "id": 58,
    "code": "VISTA",
    "isCommunityCollege": true,
    "category": "CCC",
    "termType": "Semester",
    "names": [
      {
        "name": "Vista Community College",
        "hasDepartments": true,
        "fromYear": 0,
        "hideInList": false
      },
      {
        "name": "Berkeley City College",
        "hasDepartments": true,
        "fromYear": 2006,
        "hideInList": false
      }
    ],
    "termTypeAcademicYears": [
      {
        "termType": "Semester",
        "fromYear": 2017
      },
      {
        "termType": "Semester",
        "fromYear": 2006
      },
      {
        "termType": "Semester",
        "fromYear": 1980
      }
    ]
  },
  "to": {
    "id": 88,
    "code": "SSU     ",
    "isCommunityCollege": false,
    "category": "CSU",
    "termType": "Semester",
    "names": [
      {
        "name": "Sonoma State University",
        "hasDepartments": true,
        "fromYear": 0,
        "hideInList": false
      }
    ],
    "termTypeAcademicYears": [
      {
        "termType": "Semester",
        "fromYear": 1980
      }
    ]
  },
  "agreements": [
    {
      "target": {
        "courseIdentifierParentId": 47941,
        "courseTitle": "General Physics Laboratory",
        "courseNumber": "209A",
        "prefix": "PHYS",
        "prefixParentId": 272,
        "prefixDescription": "Physics",
        "departmentParentId": 10798,
        "department": "Physics",
        "begin": "F1999",
        "end": "",
        "minUnits": 1,
        "maxUnits": 1
      },
      "courses": [
        {
          "group": "And",
          "classes": [
            {
              "visibleCrossListedCourses": [],
              "requisites": [],
              "attributes": [],
              "courseIdentifierParentId": 286519,
              "courseTitle": "General Physics",
              "courseNumber": "3A",
              "prefix": "PHYS",
              "prefixParentId": 238,
              "prefixDescription": "Physics",
              "departmentParentId": 10781,
              "department": "Physics",
              "begin": "F2009",
              "end": "",
              "minUnits": 5,
              "maxUnits": 5,
              "publishedCourseIdentifierYearTermId": null,
              "position": 0,
              "type": "Course"
            }
          ]
        }
      ]
    },
    {
      "target": {
        "courseIdentifierParentId": 222444,
        "courseTitle": "General Physics",
        "courseNumber": "210A",
        "prefix": "PHYS",
        "prefixParentId": 272,
        "prefixDescription": "Physics",
        "departmentParentId": 10798,
        "department": "Physics",
        "begin": "F1999",
        "end": "",
        "minUnits": 3,
        "maxUnits": 3
      },
      "courses": [
        {
          "group": "And",
          "classes": [
            {
              "visibleCrossListedCourses": [],
              "requisites": [],
              "attributes": [],
              "courseIdentifierParentId": 286519,
              "courseTitle": "General Physics",
              "courseNumber": "3A",
              "prefix": "PHYS",
              "prefixParentId": 238,
              "prefixDescription": "Physics",
              "departmentParentId": 10781,
              "department": "Physics",
              "begin": "F2009",
              "end": "",
              "minUnits": 5,
              "maxUnits": 5,
              "publishedCourseIdentifierYearTermId": null,
              "position": 0,
              "type": "Course"
            }
          ]
        }
      ]
    },
    {
      "target": {
        "courseIdentifierParentId": 41757,
        "courseTitle": "General Physics",
        "courseNumber": "210B",
        "prefix": "PHYS",
        "prefixParentId": 272,
        "prefixDescription": "Physics",
        "departmentParentId": 10798,
        "department": "Physics",
        "begin": "F1999",
        "end": "",
        "minUnits": 3,
        "maxUnits": 3
      },
      "courses": [
        {
          "group": "And",
          "classes": [
            {
              "visibleCrossListedCourses": [],
              "requisites": [],
              "attributes": [],
              "courseIdentifierParentId": 304773,
              "courseTitle": "General Physics",
              "courseNumber": "3B",
              "prefix": "PHYS",
              "prefixParentId": 238,
              "prefixDescription": "Physics",
              "departmentParentId": 10781,
              "department": "Physics",
              "begin": "F2009",
              "end": "",
              "minUnits": 5,
              "maxUnits": 5,
              "publishedCourseIdentifierYearTermId": null,
              "position": 0,
              "type": "Course"
            }
          ]
        }
      ]
    },
    {
      "target": {
        "courseIdentifierParentId": 293310,
        "courseTitle": "Differential & Integral Calc I",
        "courseNumber": "161",
        "prefix": "MATH",
        "prefixParentId": 9997,
        "prefixDescription": "Mathematics and Statistics",
        "departmentParentId": 9085,
        "department": "Mathematics and Statistics",
        "begin": "F2008",
        "end": "",
        "minUnits": 4,
        "maxUnits": 4
      },
      "courses": [
        {
          "group": "And",
          "classes": [
            {
              "visibleCrossListedCourses": [],
              "requisites": [],
              "attributes": [],
              "courseIdentifierParentId": 302940,
              "courseTitle": "Calculus I",
              "courseNumber": "3A",
              "prefix": "MATH",
              "prefixParentId": 9966,
              "prefixDescription": "Mathematics",
              "departmentParentId": 8994,
              "department": "Mathematics",
              "begin": "F1995",
              "end": "",
              "minUnits": 5,
              "maxUnits": 5,
              "publishedCourseIdentifierYearTermId": 179,
              "position": 0,
              "type": "Course"
            }
          ]
        }
      ]
    },
    {
      "target": {
        "courseIdentifierParentId": 354375,
        "courseTitle": "Elementary Applied Statistics",
        "courseNumber": "165",
        "prefix": "MATH",
        "prefixParentId": 9997,
        "prefixDescription": "Mathematics and Statistics",
        "departmentParentId": 9085,
        "department": "Mathematics and Statistics",
        "begin": "F2008",
        "end": "",
        "minUnits": 4,
        "maxUnits": 4
      },
      "courses": [
        {
          "group": "And",
          "classes": [
            {
              "visibleCrossListedCourses": [],
              "requisites": [],
              "attributes": [],
              "courseIdentifierParentId": 353546,
              "courseTitle": "Introduction to Statistics",
              "courseNumber": "13",
              "prefix": "MATH",
              "prefixParentId": 9966,
              "prefixDescription": "Mathematics",
              "departmentParentId": 8994,
              "department": "Mathematics",
              "begin": "F1995",
              "end": "",
              "minUnits": 4,
              "maxUnits": 4,
              "publishedCourseIdentifierYearTermId": null,
              "position": 0,
              "type": "Course"
            }
          ]
        }
      ]
    },
    {
      "courses": [
        {
          "group": "And",
          "classes": [
            {
              "visibleCrossListedCourses": [],
              "requisites": [],
              "attributes": [],
              "courseIdentifierParentId": 358859,
              "courseTitle": "General Biology",
              "courseNumber": "1A",
              "prefix": "BIOL",
              "prefixParentId": 4876,
              "prefixDescription": "Biology",
              "departmentParentId": 1713,
              "department": "Biology",
              "begin": "F1995",
              "end": "",
              "minUnits": 5,
              "maxUnits": 5,
              "publishedCourseIdentifierYearTermId": null,
              "position": 0,
              "type": "Course"
            },
            {
              "visibleCrossListedCourses": [],
              "requisites": [],
              "attributes": [],
              "courseIdentifierParentId": 302598,
              "courseTitle": "General Biology",
              "courseNumber": "1B",
              "prefix": "BIOL",
              "prefixParentId": 4876,
              "prefixDescription": "Biology",
              "departmentParentId": 1713,
              "department": "Biology",
              "begin": "F1995",
              "end": "",
              "minUnits": 5,
              "maxUnits": 5,
              "publishedCourseIdentifierYearTermId": null,
              "position": 1,
              "type": "Course"
            }
          ]
        }
      ]
    },
    {
      "courses": [
        {
          "group": "And",
          "classes": [
            {
              "visibleCrossListedCourses": [],
              "requisites": [],
              "attributes": [
                {
                  "position": 1,
                  "content": "No upper division credit"
                },
                {
                  "position": 0,
                  "content": "Content credit only"
                }
              ],
              "courseIdentifierParentId": 309316,
              "courseTitle": "Organic Chemistry",
              "courseNumber": "12B",
              "prefix": "CHEM",
              "prefixParentId": 3798,
              "prefixDescription": "Chemistry",
              "departmentParentId": 2313,
              "department": "Chemistry",
              "begin": "F2011",
              "end": "",
              "minUnits": 5,
              "maxUnits": 5,
              "publishedCourseIdentifierYearTermId": null,
              "position": 1,
              "type": "Course"
            },
            {
              "visibleCrossListedCourses": [],
              "requisites": [],
              "attributes": [
                {
                  "position": 1,
                  "content": "No upper division credit"
                },
                {
                  "position": 0,
                  "content": "Content credit only"
                }
              ],
              "courseIdentifierParentId": 309315,
              "courseTitle": "Organic Chemistry",
              "courseNumber": "12A",
              "prefix": "CHEM",
              "prefixParentId": 3798,
              "prefixDescription": "Chemistry",
              "departmentParentId": 2313,
              "department": "Chemistry",
              "begin": "F2011",
              "end": "",
              "minUnits": 5,
              "maxUnits": 5,
              "publishedCourseIdentifierYearTermId": null,
              "position": 0,
              "type": "Course"
            }
          ]
        }
      ]
    },
    {
      "courses": [
        {
          "group": "And",
          "classes": [
            {
              "visibleCrossListedCourses": [],
              "requisites": [],
              "attributes": [],
              "courseIdentifierParentId": 302781,
              "courseTitle": "General Chemistry",
              "courseNumber": "1B",
              "prefix": "CHEM",
              "prefixParentId": 3798,
              "prefixDescription": "Chemistry",
              "departmentParentId": 2313,
              "department": "Chemistry",
              "begin": "F1995",
              "end": "",
              "minUnits": 5,
              "maxUnits": 5,
              "publishedCourseIdentifierYearTermId": null,
              "position": 1,
              "type": "Course"
            },
            {
              "visibleCrossListedCourses": [],
              "requisites": [],
              "attributes": [],
              "courseIdentifierParentId": 359046,
              "courseTitle": "General Chemistry",
              "courseNumber": "1A",
              "prefix": "CHEM",
              "prefixParentId": 3798,
              "prefixDescription": "Chemistry",
              "departmentParentId": 2313,
              "department": "Chemistry",
              "begin": "F1995",
              "end": "",
              "minUnits": 5,
              "maxUnits": 5,
              "publishedCourseIdentifierYearTermId": null,
              "position": 0,
              "type": "Course"
            }
          ]
        }
      ]
    }
  ],
  "groups": {
    "LOWER DIVISION MAJOR REQUIREMENTS": [
      {
        "instruction": null,
        "sections": [
          [
            {
              "type": "Series",
              "series": {
                "conjunction": "And",
                "name": "BIOL 130, BIOL 131",
                "courses": [
                  {
                    "id": "7259e923-a4ae-4fea-8466-ed14a1d15d20",
                    "position": 0,
                    "courseIdentifierParentId": 300047,
                    "courseTitle": "Introduction Cell Biology and Genetics",
                    "courseNumber": "130",
                    "prefix": "BIOL",
                    "prefixParentId": 4906,
                    "prefixDescription": "Biology",
                    "departmentParentId": 1729,
                    "department": "Biology",
                    "begin": "F2015",
                    "end": "",
                    "minUnits": 4,
                    "maxUnits": 4
                  },
                  {
                    "id": "9e0af248-a9c2-419f-9fbb-c0a0267a1b8b",
                    "position": 1,
                    "courseIdentifierParentId": 300048,
                    "courseTitle": "Biology Diversity and Ecology",
                    "courseNumber": "131",
                    "prefix": "BIOL",
                    "prefixParentId": 4906,
                    "prefixDescription": "Biology",
                    "departmentParentId": 1729,
                    "department": "Biology",
                    "begin": "F2015",
                    "end": "",
                    "minUnits": 4,
                    "maxUnits": 4
                  }
                ]
              },
              "requisites": [],
              "visibleCrossListedCourses": [],
              "seriesAttributes": [],
              "courseAttributes": [],
              "id": "c96a5d13-ad5f-48c6-b99c-2e33c9faeca1",
              "position": 0,
              "attributes": []
            }
          ]
        ]
      }
    ],
    "SUPPORT COURSES": [
      {
        "instruction": null,
        "sections": [
          [
            {
              "type": "Course",
              "course": {
                "courseIdentifierParentId": 47941,
                "courseTitle": "General Physics Laboratory",
                "courseNumber": "209A",
                "prefix": "PHYS",
                "prefixParentId": 272,
                "prefixDescription": "Physics",
                "departmentParentId": 10798,
                "department": "Physics",
                "begin": "F1999",
                "end": "",
                "minUnits": 1,
                "maxUnits": 1
              },
              "visibleCrossListedCourses": [],
              "requisites": [],
              "courseAttributes": [],
              "id": "f2bbea73-fd86-4e84-2089-08db93657f9b",
              "position": 0,
              "attributes": []
            },
            {
              "type": "Course",
              "course": {
                "courseIdentifierParentId": 222444,
                "courseTitle": "General Physics",
                "courseNumber": "210A",
                "prefix": "PHYS",
                "prefixParentId": 272,
                "prefixDescription": "Physics",
                "departmentParentId": 10798,
                "department": "Physics",
                "begin": "F1999",
                "end": "",
                "minUnits": 3,
                "maxUnits": 3
              },
              "visibleCrossListedCourses": [],
              "requisites": [],
              "courseAttributes": [],
              "id": "4a29ad8c-34d8-4418-b4dc-022b2a98d1fd",
              "position": 0,
              "attributes": []
            },
            {
              "type": "Course",
              "course": {
                "courseIdentifierParentId": 41757,
                "courseTitle": "General Physics",
                "courseNumber": "210B",
                "prefix": "PHYS",
                "prefixParentId": 272,
                "prefixDescription": "Physics",
                "departmentParentId": 10798,
                "department": "Physics",
                "begin": "F1999",
                "end": "",
                "minUnits": 3,
                "maxUnits": 3
              },
              "visibleCrossListedCourses": [],
              "requisites": [],
              "courseAttributes": [],
              "id": "bf4e33b9-0d5c-426f-a711-f58df8745ce5",
              "position": 0,
              "attributes": []
            },
            {
              "type": "Course",
              "course": {
                "courseIdentifierParentId": 293310,
                "courseTitle": "Differential & Integral Calc I",
                "courseNumber": "161",
                "prefix": "MATH",
                "prefixParentId": 9997,
                "prefixDescription": "Mathematics and Statistics",
                "departmentParentId": 9085,
                "department": "Mathematics and Statistics",
                "begin": "F2008",
                "end": "",
                "minUnits": 4,
                "maxUnits": 4
              },
              "visibleCrossListedCourses": [],
              "requisites": [],
              "courseAttributes": [],
              "id": "78c83b83-6934-46ce-b5cd-f8fa37f490fd",
              "position": 0,
              "attributes": []
            },
            {
              "type": "Series",
              "series": {
                "conjunction": "And",
                "name": "CHEM 335A, CHEM 335B",
                "courses": [
                  {
                    "id": "df3015f2-defc-4ddf-b9c6-982af31fae55",
                    "position": 0,
                    "courseIdentifierParentId": 174628,
                    "courseTitle": "Organic Chemistry",
                    "courseNumber": "335A",
                    "prefix": "CHEM",
                    "prefixParentId": 3828,
                    "prefixDescription": "Chemistry",
                    "departmentParentId": 2336,
                    "department": "Chemistry",
                    "begin": "F2011",
                    "end": "",
                    "minUnits": 3,
                    "maxUnits": 3
                  },
                  {
                    "id": "b26bf152-5463-4f95-b15f-6e381037f8e7",
                    "position": 1,
                    "courseIdentifierParentId": 220955,
                    "courseTitle": "Organic Chemistry",
                    "courseNumber": "335B",
                    "prefix": "CHEM",
                    "prefixParentId": 3828,
                    "prefixDescription": "Chemistry",
                    "departmentParentId": 2336,
                    "department": "Chemistry",
                    "begin": "F1999",
                    "end": "",
                    "minUnits": 3,
                    "maxUnits": 3
                  }
                ]
              },
              "requisites": [],
              "visibleCrossListedCourses": [],
              "seriesAttributes": [],
              "courseAttributes": [],
              "id": "9be6fdef-8903-4513-8898-4bcb6bd29282",
              "position": 0,
              "attributes": []
            },
            {
              "type": "Course",
              "course": {
                "courseIdentifierParentId": 354375,
                "courseTitle": "Elementary Applied Statistics",
                "courseNumber": "165",
                "prefix": "MATH",
                "prefixParentId": 9997,
                "prefixDescription": "Mathematics and Statistics",
                "departmentParentId": 9085,
                "department": "Mathematics and Statistics",
                "begin": "F2008",
                "end": "",
                "minUnits": 4,
                "maxUnits": 4
              },
              "visibleCrossListedCourses": [],
              "requisites": [],
              "courseAttributes": [],
              "id": "9dda4424-ebd6-4646-a702-46eebc29d10a",
              "position": 0,
              "attributes": []
            },
            {
              "type": "Series",
              "series": {
                "conjunction": "And",
                "name": "CHEM 115A, CHEM 115B",
                "courses": [
                  {
                    "id": "4221a69a-8153-4046-b761-289d79aaaa1f",
                    "position": 0,
                    "courseIdentifierParentId": 285739,
                    "courseTitle": "General Chemistry",
                    "courseNumber": "115A",
                    "prefix": "CHEM",
                    "prefixParentId": 3828,
                    "prefixDescription": "Chemistry",
                    "departmentParentId": 2336,
                    "department": "Chemistry",
                    "begin": "Su2009",
                    "end": "",
                    "minUnits": 5,
                    "maxUnits": 5
                  },
                  {
                    "id": "1945ca57-c3f4-474d-b020-4c9196181dfa",
                    "position": 1,
                    "courseIdentifierParentId": 261063,
                    "courseTitle": "General Chemistry",
                    "courseNumber": "115B",
                    "prefix": "CHEM",
                    "prefixParentId": 3828,
                    "prefixDescription": "Chemistry",
                    "departmentParentId": 2336,
                    "department": "Chemistry",
                    "begin": "Su2009",
                    "end": "",
                    "minUnits": 5,
                    "maxUnits": 5
                  }
                ]
              },
              "requisites": [],
              "visibleCrossListedCourses": [],
              "seriesAttributes": [],
              "courseAttributes": [],
              "id": "e5d0f61b-564e-4341-80a0-5636ca040b07",
              "position": 0,
              "attributes": []
            }
          ]
        ]
      }
    ]
  }
}