{
  "major": "Engineering - Aerospace Engineering, B.S.",
  "from": {
    "id": 78,
    "code": "RCC     ",
    "isCommunityCollege": true,
    "category": "CCC",
    "termType": "Semester",
    "names": [
      {
        "name": "Riverside City College",
        "hasDepartments": true,
        "fromYear": 0,
        "hideInList": false
      }
    ],
    "termTypeAcademicYears": [
      {
        "termType": "Semester",
        "fromYear": 2016
      },
      {
        "termType": "Semester",
        "fromYear": 1980
      }
    ],
    "beginId": 0,
    "endId": null
  },
  "to": {
    "id": 39,
    "code": "SJSU    ",
    "isCommunityCollege": false,
    "category": "CSU",
    "termType": "Semester",
    "names": [
      {
        "name": "San Jose State University",
        "hasDepartments": true,
        "fromYear": 0,
        "hideInList": false
      }
    ],
    "termTypeAcademicYears": [
      {
        "termType": "Semester",
        "fromYear": 1980
      }
    ],
    "beginId": 0,
    "endId": null
  },
  "agreements": [
    {
      "target": {
        "courseIdentifierParentId": 156778,
        "courseTitle": "Calculus I",
        "courseNumber": "30",
        "prefix": "MATH",
        "prefixParentId": 9945,
        "prefixDescription": "Mathematics",
        "departmentParentId": 9079,
        "department": "Mathematics",
        "begin": "F2016",
        "end": "",
        "minUnits": 3,
        "maxUnits": 3,
        "pathways": null
      },
      "courses": [
        {
          "group": "And",
          "classes": [
            {
              "visibleCrossListedCourses": [],
              "requisites": [],
              "attributes": [],
              "courseIdentifierParentId": 289004,
              "courseTitle": "Calculus I",
              "courseNumber": "1A",
              "prefix": "MAT",
              "prefixParentId": 9986,
              "prefixDescription": "Mathematics",
              "departmentParentId": 8940,
              "department": "Mathematics",
              "begin": "F1995",
              "end": "",
              "minUnits": 4,
              "maxUnits": 4,
              "pathways": null,
              "publishedCourseIdentifierYearTermId": null,
              "position": 0,
              "type": "Course"
            }
          ]
        }
      ]
    },
    {
      "target": {
        "courseIdentifierParentId": 170210,
        "courseTitle": "Calculus II",
        "courseNumber": "31",
        "prefix": "MATH",
        "prefixParentId": 9945,
        "prefixDescription": "Mathematics",
        "departmentParentId": 9079,
        "department": "Mathematics",
        "begin": "F2016",
        "end": "",
        "minUnits": 4,
        "maxUnits": 4,
        "pathways": null
      },
      "courses": [
        {
          "group": "And",
          "classes": [
            {
              "visibleCrossListedCourses": [],
              "requisites": [],
              "attributes": [],
              "courseIdentifierParentId": 353076,
              "courseTitle": "Calculus II",
              "courseNumber": "1B",
              "prefix": "MAT",
              "prefixParentId": 9986,
              "prefixDescription": "Mathematics",
              "departmentParentId": 8940,
              "department": "Mathematics",
              "begin": "F1995",
              "end": "",
              "minUnits": 4,
              "maxUnits": 4,
              "pathways": null,
              "publishedCourseIdentifierYearTermId": null,
              "position": 0,
              "type": "Course"
            }
          ]
        }
      ]
    },
    {
      "target": {
        "courseIdentifierParentId": 276951,
        "courseTitle": "General Chemistry",
        "courseNumber": "1A",
        "prefix": "CHEM",
        "prefixParentId": 3779,
        "prefixDescription": "Chemistry",
        "departmentParentId": 2296,
        "department": "Chemistry",
        "begin": "F2016",
        "end": "",
        "minUnits": 5,
        "maxUnits": 5,
        "pathways": null
      },
      "courses": [
        {
          "group": "And",
          "classes": [
            {
              "visibleCrossListedCourses": [],
              "requisites": [],
              "attributes": [],
              "courseIdentifierParentId": 304467,
              "courseTitle": "Honors General Chemistry, I",
              "courseNumber": "1AH",
              "prefix": "CHE",
              "prefixParentId": 3818,
              "prefixDescription": "Chemistry",
              "departmentParentId": 2258,
              "department": "Chemistry",
              "begin": "F2007",
              "end": "",
              "minUnits": 5,
              "maxUnits": 5,
              "pathways": null,
              "publishedCourseIdentifierYearTermId": null,
              "position": 0,
              "type": "Course"
            }
          ]
        },
        {
          "group": "And",
          "classes": [
            {
              "visibleCrossListedCourses": [],
              "requisites": [],
              "attributes": [],
              "courseIdentifierParentId": 280564,
              "courseTitle": "General Chemistry, I",
              "courseNumber": "1A",
              "prefix": "CHE",
              "prefixParentId": 3818,
              "prefixDescription": "Chemistry",
              "departmentParentId": 2258,
              "department": "Chemistry",
              "begin": "F2001",
              "end": "",
              "minUnits": 5,
              "maxUnits": 5,
              "pathways": null,
              "publishedCourseIdentifierYearTermId": null,
              "position": 0,
              "type": "Course"
            }
          ]
        }
      ]
    },
    {
      "target": {
        "courseIdentifierParentId": 291165,
        "courseTitle": "General Physics/Electricity and Magnetism",
        "courseNumber": "51",
        "prefix": "PHYS",
        "prefixParentId": 219,
        "prefixDescription": "Physics",
        "departmentParentId": 10863,
        "department": "Physics & Astronomy",
        "begin": "F1999",
        "end": "",
        "minUnits": 4,
        "maxUnits": 4,
        "pathways": null
      },
      "courses": [
        {
          "group": "And",
          "classes": [
            {
              "visibleCrossListedCourses": [],
              "requisites": [],
              "attributes": [],
              "courseIdentifierParentId": 290135,
              "courseTitle": "Electricity and Magnetism",
              "courseNumber": "4B",
              "prefix": "PHY",
              "prefixParentId": 260,
              "prefixDescription": "Physics",
              "departmentParentId": 10732,
              "department": "Physics",
              "begin": "F1995",
              "end": "",
              "minUnits": 4,
              "maxUnits": 4,
              "pathways": null,
              "publishedCourseIdentifierYearTermId": null,
              "position": 0,
              "type": "Course"
            }
          ]
        }
      ]
    },
    {
      "target": {
        "courseIdentifierParentId": 226424,
        "courseTitle": "Calculus III",
        "courseNumber": "32",
        "prefix": "MATH",
        "prefixParentId": 9945,
        "prefixDescription": "Mathematics",
        "departmentParentId": 9079,
        "department": "Mathematics",
        "begin": "F2016",
        "end": "",
        "minUnits": 3,
        "maxUnits": 3,
        "pathways": null
      },
      "courses": [
        {
          "group": "And",
          "classes": [
            {
              "visibleCrossListedCourses": [],
              "requisites": [],
              "attributes": [],
              "courseIdentifierParentId": 289653,
              "courseTitle": "Calculus III",
              "courseNumber": "1C",
              "prefix": "MAT",
              "prefixParentId": 9986,
              "prefixDescription": "Mathematics",
              "departmentParentId": 8940,
              "department": "Mathematics",
              "begin": "F1995",
              "end": "",
              "minUnits": 4,
              "maxUnits": 4,
              "pathways": null,
              "publishedCourseIdentifierYearTermId": null,
              "position": 0,
              "type": "Course"
            }
          ]
        }
      ]
    },
    {
      "target": {
        "courseIdentifierParentId": 262230,
        "courseTitle": "General Physics/Mechanics",
        "courseNumber": "50",
        "prefix": "PHYS",
        "prefixParentId": 219,
        "prefixDescription": "Physics",
        "departmentParentId": 10863,
        "department": "Physics & Astronomy",
        "begin": "F1999",
        "end": "",
        "minUnits": 4,
        "maxUnits": 4,
        "pathways": null
      },
      "courses": [
        {
          "group": "And",
          "classes": [
            {
              "visibleCrossListedCourses": [],
              "requisites": [],
              "attributes": [],
              "courseIdentifierParentId": 353660,
              "courseTitle": "Mechanics",
              "courseNumber": "4A",
              "prefix": "PHY",
              "prefixParentId": 260,
              "prefixDescription": "Physics",
              "departmentParentId": 10732,
              "department": "Physics",
              "begin": "F1995",
              "end": "",
              "minUnits": 4,
              "maxUnits": 4,
              "pathways": null,
              "publishedCourseIdentifierYearTermId": null,
              "position": 0,
              "type": "Course"
            }
          ]
        }
      ]
    },
    {
      "target": {
        "courseIdentifierParentId": 355665,
        "courseTitle": "General Physics/Heat and Light",
        "courseNumber": "52",
        "prefix": "PHYS",
        "prefixParentId": 219,
        "prefixDescription": "Physics",
        "departmentParentId": 10863,
        "department": "Physics & Astronomy",
        "begin": "F2008",
        "end": "",
        "minUnits": 4,
        "maxUnits": 4,
        "pathways": null
      },
      "courses": [
        {
          "group": "And",
          "classes": [
            {
              "visibleCrossListedCourses": [],
              "requisites": [],
              "attributes": [],
              "courseIdentifierParentId": 253914,
              "courseTitle": "Heat, Light and Waves",
              "courseNumber": "4C",
              "prefix": "PHY",
              "prefixParentId": 260,
              "prefixDescription": "Physics",
              "departmentParentId": 10732,
              "department": "Physics",
              "begin": "F1995",
              "end": "",
              "minUnits": 4,
              "maxUnits": 4,
              "pathways": null,
              "publishedCourseIdentifierYearTermId": null,
              "position": 0,
              "type": "Course"
            }
          ]
        }
      ]
    },
    {
      "target": {
        "courseIdentifierParentId": 170445,
        "courseTitle": "Linear Algebra I",
        "courseNumber": "39",
        "prefix": "MATH",
        "prefixParentId": 9945,
        "prefixDescription": "Mathematics",
        "departmentParentId": 9079,
        "department": "Mathematics",
        "begin": "F2020",
        "end": "",
        "minUnits": 3,
        "maxUnits": 3,
        "pathways": null
      },
      "courses": [
        {
          "group": "And",
          "classes": [
            {
              "visibleCrossListedCourses": [],
              "requisites": [],
              "attributes": [],
              "courseIdentifierParentId": 339397,
              "courseTitle": "Linear Algebra",
              "courseNumber": "3",
              "prefix": "MAT",
              "prefixParentId": 9986,
              "prefixDescription": "Mathematics",
              "departmentParentId": 8940,
              "department": "Mathematics",
              "begin": "F1995",
              "end": "",
              "minUnits": 3,
              "maxUnits": 3,
              "pathways": null,
              "publishedCourseIdentifierYearTermId": null,
              "position": 0,
              "type": "Course"
            }
          ]
        }
      ]
    },
    {
      "target": {
        "courseIdentifierParentId": 156731,
        "courseTitle": "Ordinary Differential Equations for SCI & ENGR",
        "courseNumber": "33A",
        "prefix": "MATH",
        "prefixParentId": 9945,
        "prefixDescription": "Mathematics",
        "departmentParentId": 9079,
        "department": "Mathematics",
        "begin": "F2020",
        "end": "",
        "minUnits": 3,
        "maxUnits": 3,
        "pathways": null
      },
      "courses": [
        {
          "group": "And",
          "classes": [
            {
              "visibleCrossListedCourses": [],
              "requisites": [],
              "attributes": [],
              "courseIdentifierParentId": 353542,
              "courseTitle": "Differential Equations",
              "courseNumber": "2",
              "prefix": "MAT",
              "prefixParentId": 9986,
              "prefixDescription": "Mathematics",
              "departmentParentId": 8940,
              "department": "Mathematics",
              "begin": "F1995",
              "end": "",
              "minUnits": 4,
              "maxUnits": 4,
              "pathways": null,
              "publishedCourseIdentifierYearTermId": null,
              "position": 0,
              "type": "Course"
            }
          ]
        }
      ]
    },
    {
      "target": {
        "courseIdentifierParentId": 170403,
        "courseTitle": "Argument and Analysis",
        "courseNumber": "1B",
        "prefix": "ENGL",
        "prefixParentId": 2661,
        "prefixDescription": "English",
        "departmentParentId": 5081,
        "department": "English and Comparative Literature",
        "begin": "F2015",
        "end": "",
        "minUnits": 3,
        "maxUnits": 3,
        "pathways": null
      },
      "courses": [
        {
          "group": "And",
          "classes": [
            {
              "visibleCrossListedCourses": [],
              "requisites": [],
              "attributes": [],
              "courseIdentifierParentId": 176941,
              "courseTitle": "Critical Thinking and Writing",
              "courseNumber": "1B",
              "prefix": "ENG",
              "prefixParentId": 2700,
              "prefixDescription": "English",
              "departmentParentId": 4941,
              "department": "English",
              "begin": "F1997",
              "end": "",
              "minUnits": 4,
              "maxUnits": 4,
              "pathways": null,
              "publishedCourseIdentifierYearTermId": null,
              "position": 0,
              "type": "Course"
            }
          ]
        },
        {
          "group": "And",
          "classes": [
            {
              "visibleCrossListedCourses": [],
              "requisites": [],
              "attributes": [],
              "courseIdentifierParentId": 356741,
              "courseTitle": "Honors Critical Thinking and Writing",
              "courseNumber": "1BH",
              "prefix": "ENG",
              "prefixParentId": 2700,
              "prefixDescription": "English",
              "departmentParentId": 4941,
              "department": "English",
              "begin": "F2006",
              "end": "",
              "minUnits": 4,
              "maxUnits": 4,
              "pathways": null,
              "publishedCourseIdentifierYearTermId": null,
              "position": 0,
              "type": "Course"
            }
          ]
        }
      ]
    },
    {
      "target": {
        "courseIdentifierParentId": 156749,
        "courseTitle": "Introduction to Circuit Analysis",
        "courseNumber": "98",
        "prefix": "EE",
        "prefixParentId": 5972,
        "prefixDescription": "Electrical Engineering",
        "departmentParentId": 4517,
        "department": "Electrical Engineering",
        "begin": "F2016",
        "end": "",
        "minUnits": 3,
        "maxUnits": 3,
        "pathways": null
      },
      "courses": []
    },
    {
      "target": {
        "courseIdentifierParentId": 119206,
        "courseTitle": "Computer-Aided Design for Aerospace Engineers",
        "courseNumber": "20",
        "prefix": "AE",
        "prefixParentId": 15613,
        "prefixDescription": "Aerospace Engineering",
        "departmentParentId": 251,
        "department": "Aerospace Engineering",
        "begin": "F2014",
        "end": "",
        "minUnits": 2,
        "maxUnits": 2,
        "pathways": null
      },
      "courses": []
    },
    {
      "target": {
        "courseIdentifierParentId": 119207,
        "courseTitle": "Computer Programming for Aerospace Engineers",
        "courseNumber": "30",
        "prefix": "AE",
        "prefixParentId": 15613,
        "prefixDescription": "Aerospace Engineering",
        "departmentParentId": 251,
        "department": "Aerospace Engineering",
        "begin": "F2014",
        "end": "",
        "minUnits": 2,
        "maxUnits": 2,
        "pathways": null
      },
      "courses": []
    },
    {
      "target": {
        "courseIdentifierParentId": 184085,
        "courseTitle": "Introduction to Engineering",
        "courseNumber": "10",
        "prefix": "ENGR",
        "prefixParentId": 8008,
        "prefixDescription": "Interdisciplinary Engineering",
        "departmentParentId": 14122,
        "department": "Interdisciplinary Engineering",
        "begin": "F2021",
        "end": "",
        "minUnits": 3,
        "maxUnits": 3,
        "pathways": null
      },
      "courses": [
        {
          "group": "And",
          "classes": [
            {
              "visibleCrossListedCourses": [],
              "requisites": [],
              "attributes": [
                {
                  "position": 0,
                  "content": "No GE Credit given"
                }
              ],
              "courseIdentifierParentId": 243057,
              "courseTitle": "Introduction to Engineering Design",
              "courseNumber": "4",
              "prefix": "ENE",
              "prefixParentId": 3542,
              "prefixDescription": "Engineering",
              "departmentParentId": 4721,
              "department": "Engineering",
              "begin": "F2011",
              "end": "Su2024",
              "minUnits": 3.5,
              "maxUnits": 3.5,
              "pathways": null,
              "publishedCourseIdentifierYearTermId": null,
              "position": 0,
              "type": "Course"
            }
          ]
        }
      ]
    }
  ],
  "groups": {
    "SECOND COURSE IN ENGLISH COMPOSITION": [
      {
        "instruction": {
          "type": "Following",
          "id": "d83a4085-4322-46c1-7ad1-08dc55120e27",
          "selectionType": "Complete"
        },
        "sections": [
          {
            "advisements": [],
            "courses": [
              {
                "type": "Course",
                "course": {
                  "courseIdentifierParentId": 170403,
                  "courseTitle": "Argument and Analysis",
                  "courseNumber": "1B",
                  "prefix": "ENGL",
                  "prefixParentId": 2661,
                  "prefixDescription": "English",
                  "departmentParentId": 5081,
                  "department": "English and Comparative Literature",
                  "begin": "F2015",
                  "end": "",
                  "minUnits": 3,
                  "maxUnits": 3,
                  "pathways": null
                },
                "visibleCrossListedCourses": [],
                "requisites": [],
                "courseAttributes": [],
                "id": "761390a3-1bcc-43e0-b34a-e91d1bd9c458",
                "position": 0,
                "attributes": []
              }
            ]
          }
        ]
      }
    ],
    "PREPARATION FOR THE MAJOR": [
      {
        "instruction": {
          "type": "Following",
          "id": "c76cc432-3acc-4427-7ad0-08dc55120e27",
          "selectionType": "Complete"
        },
        "sections": [
          {
            "advisements": [],
            "courses": [
              {
                "type": "Course",
                "course": {
                  "courseIdentifierParentId": 156778,
                  "courseTitle": "Calculus I",
                  "courseNumber": "30",
                  "prefix": "MATH",
                  "prefixParentId": 9945,
                  "prefixDescription": "Mathematics",
                  "departmentParentId": 9079,
                  "department": "Mathematics",
                  "begin": "F2016",
                  "end": "",
                  "minUnits": 3,
                  "maxUnits": 3,
                  "pathways": null
                },
                "visibleCrossListedCourses": [],
                "requisites": [],
                "courseAttributes": [],
                "id": "666d407a-c31e-477d-9536-b3ea7363deeb",
                "position": 0,
                "attributes": []
              },
              {
                "type": "Course",
                "course": {
                  "courseIdentifierParentId": 170210,
                  "courseTitle": "Calculus II",
                  "courseNumber": "31",
                  "prefix": "MATH",
                  "prefixParentId": 9945,
                  "prefixDescription": "Mathematics",
                  "departmentParentId": 9079,
                  "department": "Mathematics",
                  "begin": "F2016",
                  "end": "",
                  "minUnits": 4,
                  "maxUnits": 4,
                  "pathways": null
                },
                "visibleCrossListedCourses": [],
                "requisites": [],
                "courseAttributes": [],
                "id": "d99b5f18-5df3-4f2f-943a-9d570310cd2d",
                "position": 0,
                "attributes": []
              },
              {
                "type": "Course",
                "course": {
                  "courseIdentifierParentId": 276951,
                  "courseTitle": "General Chemistry",
                  "courseNumber": "1A",
                  "prefix": "CHEM",
                  "prefixParentId": 3779,
                  "prefixDescription": "Chemistry",
                  "departmentParentId": 2296,
                  "department": "Chemistry",
                  "begin": "F2016",
                  "end": "",
                  "minUnits": 5,
                  "maxUnits": 5,
                  "pathways": null
                },
                "visibleCrossListedCourses": [],
                "requisites": [],
                "courseAttributes": [],
                "id": "73be4b4e-66dc-438e-8f5b-ba93e1151bef",
                "position": 0,
                "attributes": []
              },
              {
                "type": "Course",
                "course": {
                  "courseIdentifierParentId": 291165,
                  "courseTitle": "General Physics/Electricity and Magnetism",
                  "courseNumber": "51",
                  "prefix": "PHYS",
                  "prefixParentId": 219,
                  "prefixDescription": "Physics",
                  "departmentParentId": 10863,
                  "department": "Physics & Astronomy",
                  "begin": "F1999",
                  "end": "",
                  "minUnits": 4,
                  "maxUnits": 4,
                  "pathways": null
                },
                "visibleCrossListedCourses": [],
                "requisites": [],
                "courseAttributes": [],
                "id": "1f25408e-2c4e-46ec-a32b-d0d5cf745eff",
                "position": 0,
                "attributes": []
              },
              {
                "type": "Course",
                "course": {
                  "courseIdentifierParentId": 226424,
                  "courseTitle": "Calculus III",
                  "courseNumber": "32",
                  "prefix": "MATH",
                  "prefixParentId": 9945,
                  "prefixDescription": "Mathematics",
                  "departmentParentId": 9079,
                  "department": "Mathematics",
                  "begin": "F2016",
                  "end": "",
                  "minUnits": 3,
                  "maxUnits": 3,
                  "pathways": null
                },
                "visibleCrossListedCourses": [],
                "requisites": [],
                "courseAttributes": [],
                "id": "4b30f842-7fe6-41cb-b21c-9cad89241255",
                "position": 0,
                "attributes": []
              },
              {
                "type": "Course",
                "course": {
                  "courseIdentifierParentId": 262230,
                  "courseTitle": "General Physics/Mechanics",
                  "courseNumber": "50",
                  "prefix": "PHYS",
                  "prefixParentId": 219,
                  "prefixDescription": "Physics",
                  "departmentParentId": 10863,
                  "department": "Physics & Astronomy",
                  "begin": "F1999",
                  "end": "",
                  "minUnits": 4,
                  "maxUnits": 4,
                  "pathways": null
                },
                "visibleCrossListedCourses": [],
                "requisites": [],
                "courseAttributes": [],
                "id": "407581a6-b597-4496-bc05-1e815a96d580",
                "position": 0,
                "attributes": []
              },
              {
                "type": "Course",
                "course": {
                  "courseIdentifierParentId": 355665,
                  "courseTitle": "General Physics/Heat and Light",
                  "courseNumber": "52",
                  "prefix": "PHYS",
                  "prefixParentId": 219,
                  "prefixDescription": "Physics",
                  "departmentParentId": 10863,
                  "department": "Physics & Astronomy",
                  "begin": "F2008",
                  "end": "",
                  "minUnits": 4,
                  "maxUnits": 4,
                  "pathways": null
                },
                "visibleCrossListedCourses": [],
                "requisites": [],
                "courseAttributes": [],
                "id": "f25524f7-eac1-4c0b-96d7-eba31541b221",
                "position": 0,
                "attributes": []
              },
              {
                "type": "Course",
                "course": {
                  "courseIdentifierParentId": 170445,
                  "courseTitle": "Linear Algebra I",
                  "courseNumber": "39",
                  "prefix": "MATH",
                  "prefixParentId": 9945,
                  "prefixDescription": "Mathematics",
                  "departmentParentId": 9079,
                  "department": "Mathematics",
                  "begin": "F2020",
                  "end": "",
                  "minUnits": 3,
                  "maxUnits": 3,
                  "pathways": null
                },
                "visibleCrossListedCourses": [],
                "requisites": [],
                "courseAttributes": [],
                "id": "13c380b9-fb2a-47a1-9ec6-c4c559d5dc0e",
                "position": 0,
                "attributes": []
              },
              {
                "type": "Course",
                "course": {
                  "courseIdentifierParentId": 156731,
                  "courseTitle": "Ordinary Differential Equations for SCI & ENGR",
                  "courseNumber": "33A",
                  "prefix": "MATH",
                  "prefixParentId": 9945,
                  "prefixDescription": "Mathematics",
                  "departmentParentId": 9079,
                  "department": "Mathematics",
                  "begin": "F2020",
                  "end": "",
                  "minUnits": 3,
                  "maxUnits": 3,
                  "pathways": null
                },
                "visibleCrossListedCourses": [],
                "requisites": [],
                "courseAttributes": [],
                "id": "905ac127-1f7a-4525-979c-41eda53185e3",
                "position": 0,
                "attributes": []
              }
            ]
          }
        ]
      }
    ],
    "LOWER DIVISION CORE REQUIREMENTS OF THE MAJOR": [
      {
        "instruction": {
          "type": "Following",
          "id": "7ffc78bc-64dc-41d5-7ad2-08dc55120e27",
          "selectionType": "Complete"
        },
        "sections": [
          {
            "advisements": [],
            "courses": [
              {
                "type": "Course",
                "course": {
                  "courseIdentifierParentId": 156749,
                  "courseTitle": "Introduction to Circuit Analysis",
                  "courseNumber": "98",
                  "prefix": "EE",
                  "prefixParentId": 5972,
                  "prefixDescription": "Electrical Engineering",
                  "departmentParentId": 4517,
                  "department": "Electrical Engineering",
                  "begin": "F2016",
                  "end": "",
                  "minUnits": 3,
                  "maxUnits": 3,
                  "pathways": null
                },
                "visibleCrossListedCourses": [],
                "requisites": [],
                "courseAttributes": [],
                "id": "08190e72-9b04-45e0-9231-37fe079a0a5e",
                "position": 0,
                "attributes": []
              },
              {
                "type": "Course",
                "course": {
                  "courseIdentifierParentId": 119206,
                  "courseTitle": "Computer-Aided Design for Aerospace Engineers",
                  "courseNumber": "20",
                  "prefix": "AE",
                  "prefixParentId": 15613,
                  "prefixDescription": "Aerospace Engineering",
                  "departmentParentId": 251,
                  "department": "Aerospace Engineering",
                  "begin": "F2014",
                  "end": "",
                  "minUnits": 2,
                  "maxUnits": 2,
                  "pathways": null
                },
                "visibleCrossListedCourses": [],
                "requisites": [],
                "courseAttributes": [],
                "id": "7edc7da3-5491-48f7-a9b2-7ffe1b70a59a",
                "position": 0,
                "attributes": []
              },
              {
                "type": "Course",
                "course": {
                  "courseIdentifierParentId": 119207,
                  "courseTitle": "Computer Programming for Aerospace Engineers",
                  "courseNumber": "30",
                  "prefix": "AE",
                  "prefixParentId": 15613,
                  "prefixDescription": "Aerospace Engineering",
                  "departmentParentId": 251,
                  "department": "Aerospace Engineering",
                  "begin": "F2014",
                  "end": "",
                  "minUnits": 2,
                  "maxUnits": 2,
                  "pathways": null
                },
                "visibleCrossListedCourses": [],
                "requisites": [],
                "courseAttributes": [],
                "id": "e23f3ef1-3c49-437e-815c-fc1205939674",
                "position": 0,
                "attributes": []
              },
              {
                "type": "Course",
                "course": {
                  "courseIdentifierParentId": 184085,
                  "courseTitle": "Introduction to Engineering",
                  "courseNumber": "10",
                  "prefix": "ENGR",
                  "prefixParentId": 8008,
                  "prefixDescription": "Interdisciplinary Engineering",
                  "departmentParentId": 14122,
                  "department": "Interdisciplinary Engineering",
                  "begin": "F2021",
                  "end": "",
                  "minUnits": 3,
                  "maxUnits": 3,
                  "pathways": null
                },
                "visibleCrossListedCourses": [],
                "requisites": [],
                "courseAttributes": [],
                "id": "15c1829a-1915-4561-a2ba-1e37a573ca4b",
                "position": 0,
                "attributes": []
              }
            ]
          }
        ]
      }
    ]
  }
}