{
  "major": "Economics, Quantitative Economics Emphasis, B.S.",
  "from": {
    "id": 71,
    "code": "CYPRESS ",
    "isCommunityCollege": true,
    "category": "CCC",
    "termType": "Semester",
    "names": [
      {
        "name": "Cypress College",
        "hasDepartments": true,
        "fromYear": 0,
        "hideInList": false
      }
    ],
    "termTypeAcademicYears": [
      {
        "termType": "Semester",
        "fromYear": 1980
      }
    ]
  },
  "to": {
    "id": 144,
    "code": "UCM     ",
    "isCommunityCollege": false,
    "category": "UC",
    "termType": "Semester",
    "names": [
      {
        "name": "University of California, Merced",
        "hasDepartments": true,
        "fromYear": 0,
        "hideInList": false
      }
    ],
    "termTypeAcademicYears": [
      {
        "termType": "Semester",
        "fromYear": 2002
      }
    ]
  },
  "agreements": [
    {
      "target": {
        "courseIdentifierParentId": 299506,
        "courseTitle": "Introduction to Sociocultural Anthropology",
        "courseNumber": "001",
        "prefix": "ANTH",
        "prefixParentId": 13940,
        "prefixDescription": "Anthropology",
        "departmentParentId": 769,
        "department": "Anthropology",
        "begin": "F2019",
        "end": "",
        "minUnits": 4,
        "maxUnits": 4
      },
      "courses": [
        {
          "group": "And",
          "classes": [
            {
              "visibleCrossListedCourses": [],
              "requisites": [],
              "attributes": [],
              "courseIdentifierParentId": 185531,
              "courseTitle": "Cultural Anthropology",
              "courseNumber": "102 C",
              "prefix": "ANTH",
              "prefixParentId": 10752,
              "prefixDescription": "Anthropology",
              "departmentParentId": 724,
              "department": "Anthropology",
              "begin": "F2002",
              "end": "",
              "minUnits": 3,
              "maxUnits": 3,
              "publishedCourseIdentifierYearTermId": null,
              "position": 0,
              "type": "Course"
            }
          ]
        }
      ]
    },
    {
      "target": {
        "courseIdentifierParentId": 273195,
        "courseTitle": "Introduction to Public Health",
        "courseNumber": "001",
        "prefix": "PH",
        "prefixParentId": 15646,
        "prefixDescription": "Public Health",
        "departmentParentId": 11343,
        "department": "Public Health",
        "begin": "F2019",
        "end": "",
        "minUnits": 4,
        "maxUnits": 4
      },
      "courses": [
        {
          "group": "And",
          "classes": [
            {
              "visibleCrossListedCourses": [],
              "requisites": [],
              "attributes": [],
              "courseIdentifierParentId": 239344,
              "courseTitle": "Introduction to Public Health",
              "courseNumber": "280 C",
              "prefix": "PHS",
              "prefixParentId": 16808,
              "prefixDescription": "Public Health Science",
              "departmentParentId": 13924,
              "department": "Public Health Science ",
              "begin": "F2021",
              "end": "",
              "minUnits": 3,
              "maxUnits": 3,
              "publishedCourseIdentifierYearTermId": null,
              "position": 0,
              "type": "Course"
            }
          ]
        },
        {
          "group": "And",
          "classes": [
            {
              "visibleCrossListedCourses": [],
              "requisites": [],
              "attributes": [],
              "courseIdentifierParentId": 372654,
              "courseTitle": "Honors Introduction to Public Health",
              "courseNumber": "280HC",
              "prefix": "PHS",
              "prefixParentId": 16808,
              "prefixDescription": "Public Health Science",
              "departmentParentId": 13924,
              "department": "Public Health Science ",
              "begin": "F2021",
              "end": "",
              "minUnits": 3,
              "maxUnits": 3,
              "publishedCourseIdentifierYearTermId": null,
              "position": 0,
              "type": "Course"
            }
          ]
        }
      ]
    },
    {
      "target": {
        "courseIdentifierParentId": 304580,
        "courseTitle": "Global and International Public Health",
        "courseNumber": "005",
        "prefix": "PH",
        "prefixParentId": 15646,
        "prefixDescription": "Public Health",
        "departmentParentId": 11343,
        "department": "Public Health",
        "begin": "F2019",
        "end": "",
        "minUnits": 4,
        "maxUnits": 4
      },
      "courses": [
        {
          "group": "And",
          "classes": [
            {
              "visibleCrossListedCourses": [],
              "requisites": [],
              "attributes": [],
              "courseIdentifierParentId": 275720,
              "courseTitle": "Global and Community Health",
              "courseNumber": "285 C",
              "prefix": "PHS",
              "prefixParentId": 16808,
              "prefixDescription": "Public Health Science",
              "departmentParentId": 13924,
              "department": "Public Health Science ",
              "begin": "F2021",
              "end": "",
              "minUnits": 3,
              "maxUnits": 3,
              "publishedCourseIdentifierYearTermId": null,
              "position": 0,
              "type": "Course"
            }
          ]
        }
      ]
    },
    {
      "target": {
        "courseIdentifierParentId": 269488,
        "courseTitle": "Introduction to Psychology",
        "courseNumber": "001",
        "prefix": "PSY",
        "prefixParentId": 13961,
        "prefixDescription": "Psychology",
        "departmentParentId": 11217,
        "department": "Psychology",
        "begin": "F2019",
        "end": "",
        "minUnits": 4,
        "maxUnits": 4
      },
      "courses": [
        {
          "group": "And",
          "classes": [
            {
              "visibleCrossListedCourses": [],
              "requisites": [],
              "attributes": [],
              "courseIdentifierParentId": 346084,
              "courseTitle": "Honors Intro to Psychology",
              "courseNumber": "101HC",
              "prefix": "PSY",
              "prefixParentId": 4660,
              "prefixDescription": "Psychology",
              "departmentParentId": 11197,
              "department": "Psychology",
              "begin": "F2012",
              "end": "",
              "minUnits": 3,
              "maxUnits": 3,
              "publishedCourseIdentifierYearTermId": null,
              "position": 0,
              "type": "Course"
            }
          ]
        },
        {
          "group": "And",
          "classes": [
            {
              "visibleCrossListedCourses": [],
              "requisites": [],
              "attributes": [],
              "courseIdentifierParentId": 201047,
              "courseTitle": "Introduction to Psychology",
              "courseNumber": "101 C",
              "prefix": "PSY",
              "prefixParentId": 4660,
              "prefixDescription": "Psychology",
              "departmentParentId": 11197,
              "department": "Psychology",
              "begin": "F2012",
              "end": "",
              "minUnits": 3,
              "maxUnits": 3,
              "publishedCourseIdentifierYearTermId": null,
              "position": 0,
              "type": "Course"
            }
          ]
        }
      ]
    },
    {
      "target": {
        "courseIdentifierParentId": 356657,
        "courseTitle": "Introduction to American Politics",
        "courseNumber": "001",
        "prefix": "POLI",
        "prefixParentId": 13960,
        "prefixDescription": "Political Science",
        "departmentParentId": 11019,
        "department": "Political Science",
        "begin": "F2019",
        "end": "",
        "minUnits": 4,
        "maxUnits": 4
      },
      "courses": [
        {
          "group": "And",
          "classes": [
            {
              "visibleCrossListedCourses": [],
              "requisites": [],
              "attributes": [],
              "courseIdentifierParentId": 144220,
              "courseTitle": "United States Government",
              "courseNumber": "100 C",
              "prefix": "POSC",
              "prefixParentId": 1962,
              "prefixDescription": "Political Science",
              "departmentParentId": 11068,
              "department": "Political Science",
              "begin": "F2004",
              "end": "",
              "minUnits": 3,
              "maxUnits": 3,
              "publishedCourseIdentifierYearTermId": null,
              "position": 0,
              "type": "Course"
            }
          ]
        },
        {
          "group": "And",
          "classes": [
            {
              "visibleCrossListedCourses": [],
              "requisites": [],
              "attributes": [],
              "courseIdentifierParentId": 341912,
              "courseTitle": "Honors United States Government",
              "courseNumber": "100HC",
              "prefix": "POSC",
              "prefixParentId": 1962,
              "prefixDescription": "Political Science",
              "departmentParentId": 11068,
              "department": "Political Science",
              "begin": "F2011",
              "end": "",
              "minUnits": 3,
              "maxUnits": 3,
              "publishedCourseIdentifierYearTermId": null,
              "position": 0,
              "type": "Course"
            }
          ]
        }
      ]
    },
    {
      "target": {
        "courseIdentifierParentId": 299521,
        "courseTitle": "Introduction to Sociology",
        "courseNumber": "001",
        "prefix": "SOC",
        "prefixParentId": 13963,
        "prefixDescription": "Sociology",
        "departmentParentId": 12129,
        "department": "Sociology",
        "begin": "F2019",
        "end": "",
        "minUnits": 4,
        "maxUnits": 4
      },
      "courses": [
        {
          "group": "And",
          "classes": [
            {
              "visibleCrossListedCourses": [],
              "requisites": [],
              "attributes": [],
              "courseIdentifierParentId": 250197,
              "courseTitle": "Honors Intro to Sociology",
              "courseNumber": "101HC",
              "prefix": "SOC",
              "prefixParentId": 9045,
              "prefixDescription": "Sociology",
              "departmentParentId": 12079,
              "department": "Sociology",
              "begin": "F2005",
              "end": "",
              "minUnits": 3,
              "maxUnits": 3,
              "publishedCourseIdentifierYearTermId": null,
              "position": 0,
              "type": "Course"
            }
          ]
        },
        {
          "group": "And",
          "classes": [
            {
              "visibleCrossListedCourses": [],
              "requisites": [],
              "attributes": [],
              "courseIdentifierParentId": 170934,
              "courseTitle": "Introduction to Sociology",
              "courseNumber": "101 C",
              "prefix": "SOC",
              "prefixParentId": 9045,
              "prefixDescription": "Sociology",
              "departmentParentId": 12079,
              "department": "Sociology",
              "begin": "F2002",
              "end": "",
              "minUnits": 3,
              "maxUnits": 3,
              "publishedCourseIdentifierYearTermId": null,
              "position": 0,
              "type": "Course"
            }
          ]
        }
      ]
    },
    {
      "target": {
        "courseIdentifierParentId": 269491,
        "courseTitle": "Academic Writing",
        "courseNumber": "001",
        "prefix": "WRI",
        "prefixParentId": 13965,
        "prefixDescription": "Writing",
        "departmentParentId": 13255,
        "department": "Writing",
        "begin": "F2019",
        "end": "",
        "minUnits": 4,
        "maxUnits": 4
      },
      "courses": [
        {
          "group": "And",
          "classes": [
            {
              "visibleCrossListedCourses": [],
              "requisites": [],
              "attributes": [
                {
                  "position": 0,
                  "content": "UC credit limitation applies; refer to UC-transferability list"
                }
              ],
              "courseIdentifierParentId": 372630,
              "courseTitle": "Enhanced College Writing",
              "courseNumber": "101 C",
              "prefix": "ENGL",
              "prefixParentId": 2693,
              "prefixDescription": "English",
              "departmentParentId": 4996,
              "department": "English",
              "begin": "F2020",
              "end": "",
              "minUnits": 5,
              "maxUnits": 5,
              "publishedCourseIdentifierYearTermId": null,
              "position": 0,
              "type": "Course"
            }
          ]
        },
        {
          "group": "And",
          "classes": [
            {
              "visibleCrossListedCourses": [],
              "requisites": [],
              "attributes": [],
              "courseIdentifierParentId": 144185,
              "courseTitle": "College Writing",
              "courseNumber": "100 C",
              "prefix": "ENGL",
              "prefixParentId": 2693,
              "prefixDescription": "English",
              "departmentParentId": 4996,
              "department": "English",
              "begin": "F2013",
              "end": "",
              "minUnits": 4,
              "maxUnits": 4,
              "publishedCourseIdentifierYearTermId": null,
              "position": 0,
              "type": "Course"
            }
          ]
        },
        {
          "group": "And",
          "classes": [
            {
              "visibleCrossListedCourses": [],
              "requisites": [],
              "attributes": [],
              "courseIdentifierParentId": 200581,
              "courseTitle": "Honors College Writing",
              "courseNumber": "100HC",
              "prefix": "ENGL",
              "prefixParentId": 2693,
              "prefixDescription": "English",
              "departmentParentId": 4996,
              "department": "English",
              "begin": "F2013",
              "end": "",
              "minUnits": 4,
              "maxUnits": 4,
              "publishedCourseIdentifierYearTermId": null,
              "position": 0,
              "type": "Course"
            }
          ]
        },
        {
          "group": "And",
          "classes": [
            {
              "visibleCrossListedCourses": [],
              "requisites": [],
              "attributes": [],
              "courseIdentifierParentId": 372646,
              "courseTitle": "College Composition for Non-Native Speakers",
              "courseNumber": "110 C",
              "prefix": "ESL",
              "prefixParentId": 4188,
              "prefixDescription": "English as a Second Language",
              "departmentParentId": 5124,
              "department": "English as a Second Language",
              "begin": "F2020",
              "end": "",
              "minUnits": 5,
              "maxUnits": 5,
              "publishedCourseIdentifierYearTermId": null,
              "position": 0,
              "type": "Course"
            }
          ]
        }
      ]
    },
    {
      "target": {
        "courseIdentifierParentId": 296253,
        "courseTitle": "College Reading and Composition",
        "courseNumber": "010",
        "prefix": "WRI",
        "prefixParentId": 13965,
        "prefixDescription": "Writing",
        "departmentParentId": 13255,
        "department": "Writing",
        "begin": "F2019",
        "end": "",
        "minUnits": 4,
        "maxUnits": 4
      },
      "courses": [
        {
          "group": "And",
          "classes": [
            {
              "visibleCrossListedCourses": [],
              "requisites": [],
              "attributes": [],
              "courseIdentifierParentId": 187558,
              "courseTitle": "Critical Thinking and Writing",
              "courseNumber": "172 C",
              "prefix": "PHIL",
              "prefixParentId": 1786,
              "prefixDescription": "Philosophy and Religious Studies",
              "departmentParentId": 10233,
              "department": "Philosophy and Religious Studies",
              "begin": "F2016",
              "end": "",
              "minUnits": 3,
              "maxUnits": 3,
              "publishedCourseIdentifierYearTermId": null,
              "position": 0,
              "type": "Course"
            }
          ]
        },
        {
          "group": "And",
          "classes": [
            {
              "visibleCrossListedCourses": [],
              "requisites": [],
              "attributes": [],
              "courseIdentifierParentId": 181371,
              "courseTitle": "Honors Critical Analysis & Lit",
              "courseNumber": "104HC",
              "prefix": "ENGL",
              "prefixParentId": 2693,
              "prefixDescription": "English",
              "departmentParentId": 4996,
              "department": "English",
              "begin": "F2002",
              "end": "",
              "minUnits": 4,
              "maxUnits": 4,
              "publishedCourseIdentifierYearTermId": null,
              "position": 0,
              "type": "Course"
            }
          ]
        },
        {
          "group": "And",
          "classes": [
            {
              "visibleCrossListedCourses": [],
              "requisites": [],
              "attributes": [],
              "courseIdentifierParentId": 144459,
              "courseTitle": "Critical Reasoning and Writing",
              "courseNumber": "103 C",
              "prefix": "ENGL",
              "prefixParentId": 2693,
              "prefixDescription": "English",
              "departmentParentId": 4996,
              "department": "English",
              "begin": "F2014",
              "end": "",
              "minUnits": 4,
              "maxUnits": 4,
              "publishedCourseIdentifierYearTermId": null,
              "position": 0,
              "type": "Course"
            }
          ]
        },
        {
          "group": "And",
          "classes": [
            {
              "visibleCrossListedCourses": [],
              "requisites": [],
              "attributes": [],
              "courseIdentifierParentId": 181363,
              "courseTitle": "Critical Analysis & Literature",
              "courseNumber": "104 C",
              "prefix": "ENGL",
              "prefixParentId": 2693,
              "prefixDescription": "English",
              "departmentParentId": 4996,
              "department": "English",
              "begin": "F2002",
              "end": "",
              "minUnits": 4,
              "maxUnits": 4,
              "publishedCourseIdentifierYearTermId": null,
              "position": 0,
              "type": "Course"
            }
          ]
        },
        {
          "group": "And",
          "classes": [
            {
              "visibleCrossListedCourses": [],
              "requisites": [],
              "attributes": [],
              "courseIdentifierParentId": 299824,
              "courseTitle": "Honors Critical Reasoning and Writing",
              "courseNumber": "103HC",
              "prefix": "ENGL",
              "prefixParentId": 2693,
              "prefixDescription": "English",
              "departmentParentId": 4996,
              "department": "English",
              "begin": "F2015",
              "end": "",
              "minUnits": 4,
              "maxUnits": 4,
              "publishedCourseIdentifierYearTermId": null,
              "position": 0,
              "type": "Course"
            }
          ]
        }
      ]
    },
    {
      "target": {
        "courseIdentifierParentId": 299518,
        "courseTitle": "Linear Algebra and Differential Equations",
        "courseNumber": "024",
        "prefix": "MATH",
        "prefixParentId": 13957,
        "prefixDescription": "Mathematics",
        "departmentParentId": 9070,
        "department": "Mathematics",
        "begin": "F2019",
        "end": "",
        "minUnits": 4,
        "maxUnits": 4
      },
      "courses": [
        {
          "group": "And",
          "classes": [
            {
              "visibleCrossListedCourses": [],
              "requisites": [],
              "attributes": [],
              "courseIdentifierParentId": 297855,
              "courseTitle": "Linear Algebra and Differential Equations",
              "courseNumber": "250BC",
              "prefix": "MATH",
              "prefixParentId": 9978,
              "prefixDescription": "Mathematics",
              "departmentParentId": 9004,
              "department": "Mathematics",
              "begin": "F2018",
              "end": "",
              "minUnits": 5,
              "maxUnits": 5,
              "publishedCourseIdentifierYearTermId": null,
              "position": 0,
              "type": "Course"
            }
          ]
        }
      ]
    },
    {
      "target": {
        "courseIdentifierParentId": 299516,
        "courseTitle": "Vector Calculus",
        "courseNumber": "023",
        "prefix": "MATH",
        "prefixParentId": 13957,
        "prefixDescription": "Mathematics",
        "departmentParentId": 9070,
        "department": "Mathematics",
        "begin": "F2019",
        "end": "",
        "minUnits": 4,
        "maxUnits": 4
      },
      "courses": [
        {
          "group": "And",
          "classes": [
            {
              "visibleCrossListedCourses": [],
              "requisites": [],
              "attributes": [],
              "courseIdentifierParentId": 278536,
              "courseTitle": "Multivariable Calculus",
              "courseNumber": "250AC",
              "prefix": "MATH",
              "prefixParentId": 9978,
              "prefixDescription": "Mathematics",
              "departmentParentId": 9004,
              "department": "Mathematics",
              "begin": "F2008",
              "end": "",
              "minUnits": 4,
              "maxUnits": 4,
              "publishedCourseIdentifierYearTermId": null,
              "position": 0,
              "type": "Course"
            }
          ]
        }
      ]
    },
    {
      "target": {
        "courseIdentifierParentId": 356654,
        "courseTitle": "Introduction to Economics",
        "courseNumber": "001",
        "prefix": "ECON",
        "prefixParentId": 13949,
        "prefixDescription": "Economics",
        "departmentParentId": 4341,
        "department": "Economics",
        "begin": "F2019",
        "end": "",
        "minUnits": 4,
        "maxUnits": 4
      },
      "courses": [
        {
          "group": "And",
          "classes": [
            {
              "visibleCrossListedCourses": [],
              "requisites": [],
              "attributes": [],
              "courseIdentifierParentId": 201186,
              "courseTitle": "Honors Principles of Economics",
              "courseNumber": "105HC",
              "prefix": "ECON",
              "prefixParentId": 1245,
              "prefixDescription": "Economics",
              "departmentParentId": 4274,
              "department": "Economics",
              "begin": "F2002",
              "end": "",
              "minUnits": 3,
              "maxUnits": 3,
              "publishedCourseIdentifierYearTermId": null,
              "position": 0,
              "type": "Course"
            }
          ]
        },
        {
          "group": "And",
          "classes": [
            {
              "visibleCrossListedCourses": [],
              "requisites": [],
              "attributes": [],
              "courseIdentifierParentId": 232567,
              "courseTitle": "Honors Principles of Economics",
              "courseNumber": "100HC",
              "prefix": "ECON",
              "prefixParentId": 1245,
              "prefixDescription": "Economics",
              "departmentParentId": 4274,
              "department": "Economics",
              "begin": "F2004",
              "end": "",
              "minUnits": 3,
              "maxUnits": 3,
              "publishedCourseIdentifierYearTermId": null,
              "position": 0,
              "type": "Course"
            },
            {
              "visibleCrossListedCourses": [],
              "requisites": [],
              "attributes": [],
              "courseIdentifierParentId": 171596,
              "courseTitle": "Principles of Economics-MICRO",
              "courseNumber": "105 C",
              "prefix": "ECON",
              "prefixParentId": 1245,
              "prefixDescription": "Economics",
              "departmentParentId": 4274,
              "department": "Economics",
              "begin": "F2004",
              "end": "",
              "minUnits": 3,
              "maxUnits": 3,
              "publishedCourseIdentifierYearTermId": null,
              "position": 1,
              "type": "Course"
            }
          ]
        },
        {
          "group": "And",
          "classes": [
            {
              "visibleCrossListedCourses": [],
              "requisites": [],
              "attributes": [],
              "courseIdentifierParentId": 144783,
              "courseTitle": "Principles of Economics-MACRO",
              "courseNumber": "100 C",
              "prefix": "ECON",
              "prefixParentId": 1245,
              "prefixDescription": "Economics",
              "departmentParentId": 4274,
              "department": "Economics",
              "begin": "F2004",
              "end": "",
              "minUnits": 3,
              "maxUnits": 3,
              "publishedCourseIdentifierYearTermId": null,
              "position": 0,
              "type": "Course"
            }
          ]
        }
      ]
    },
    {
      "target": {
        "courseIdentifierParentId": 296244,
        "courseTitle": "Calculus II for Physical Sciences & Engineering",
        "courseNumber": "022",
        "prefix": "MATH",
        "prefixParentId": 13957,
        "prefixDescription": "Mathematics",
        "departmentParentId": 9070,
        "department": "Mathematics",
        "begin": "F2019",
        "end": "",
        "minUnits": 4,
        "maxUnits": 4
      },
      "courses": [
        {
          "group": "And",
          "classes": [
            {
              "visibleCrossListedCourses": [],
              "requisites": [],
              "attributes": [],
              "courseIdentifierParentId": 248691,
              "courseTitle": "Calculus II",
              "courseNumber": "150BC",
              "prefix": "MATH",
              "prefixParentId": 9978,
              "prefixDescription": "Mathematics",
              "departmentParentId": 9004,
              "department": "Mathematics",
              "begin": "F2008",
              "end": "",
              "minUnits": 4,
              "maxUnits": 4,
              "publishedCourseIdentifierYearTermId": null,
              "position": 0,
              "type": "Course"
            }
          ]
        }
      ]
    },
    {
      "target": {
        "courseIdentifierParentId": 269482,
        "courseTitle": "Calculus I for Physical Sciences & Engineering",
        "courseNumber": "021",
        "prefix": "MATH",
        "prefixParentId": 13957,
        "prefixDescription": "Mathematics",
        "departmentParentId": 9070,
        "department": "Mathematics",
        "begin": "F2019",
        "end": "",
        "minUnits": 4,
        "maxUnits": 4
      },
      "courses": [
        {
          "group": "And",
          "classes": [
            {
              "visibleCrossListedCourses": [],
              "requisites": [],
              "attributes": [],
              "courseIdentifierParentId": 265535,
              "courseTitle": "Calculus I",
              "courseNumber": "150AC",
              "prefix": "MATH",
              "prefixParentId": 9978,
              "prefixDescription": "Mathematics",
              "departmentParentId": 9004,
              "department": "Mathematics",
              "begin": "F2008",
              "end": "",
              "minUnits": 4,
              "maxUnits": 4,
              "publishedCourseIdentifierYearTermId": null,
              "position": 0,
              "type": "Course"
            }
          ]
        }
      ]
    },
    {
      "target": {
        "courseIdentifierParentId": 356647,
        "courseTitle": "Nutrition",
        "courseNumber": "060",
        "prefix": "BIO",
        "prefixParentId": 13943,
        "prefixDescription": "Biological Sciences",
        "departmentParentId": 1651,
        "department": "Biological Sciences",
        "begin": "F2019",
        "end": "",
        "minUnits": 4,
        "maxUnits": 4
      },
      "courses": [
        {
          "group": "And",
          "classes": [
            {
              "visibleCrossListedCourses": [],
              "requisites": [],
              "attributes": [],
              "courseIdentifierParentId": 372653,
              "courseTitle": "Honors Nutrition: Science and Application",
              "courseNumber": "270HC",
              "prefix": "PHS",
              "prefixParentId": 16808,
              "prefixDescription": "Public Health Science",
              "departmentParentId": 13924,
              "department": "Public Health Science ",
              "begin": "F2021",
              "end": "",
              "minUnits": 3,
              "maxUnits": 3,
              "publishedCourseIdentifierYearTermId": null,
              "position": 0,
              "type": "Course"
            }
          ]
        },
        {
          "group": "And",
          "classes": [
            {
              "visibleCrossListedCourses": [],
              "requisites": [],
              "attributes": [],
              "courseIdentifierParentId": 377379,
              "courseTitle": "Nutrition for Public Health",
              "courseNumber": "286 C",
              "prefix": "PHS",
              "prefixParentId": 16808,
              "prefixDescription": "Public Health Science",
              "departmentParentId": 13924,
              "department": "Public Health Science ",
              "begin": "F2023",
              "end": "",
              "minUnits": 3,
              "maxUnits": 3,
              "publishedCourseIdentifierYearTermId": null,
              "position": 0,
              "type": "Course"
            }
          ]
        },
        {
          "group": "And",
          "classes": [
            {
              "visibleCrossListedCourses": [],
              "requisites": [],
              "attributes": [],
              "courseIdentifierParentId": 145415,
              "courseTitle": "Nutrition",
              "courseNumber": "100 C",
              "prefix": "HRC",
              "prefixParentId": 8036,
              "prefixDescription": "Hotel, Restaurant, Culinary Arts",
              "departmentParentId": 7161,
              "department": "Hospitality and Travel Careers",
              "begin": "F2002",
              "end": "",
              "minUnits": 3,
              "maxUnits": 3,
              "publishedCourseIdentifierYearTermId": null,
              "position": 0,
              "type": "Course"
            }
          ]
        },
        {
          "group": "And",
          "classes": [
            {
              "visibleCrossListedCourses": [],
              "requisites": [],
              "attributes": [],
              "courseIdentifierParentId": 275718,
              "courseTitle": "Nutrition - Science and Application",
              "courseNumber": "270 C",
              "prefix": "PHS",
              "prefixParentId": 16808,
              "prefixDescription": "Public Health Science",
              "departmentParentId": 13924,
              "department": "Public Health Science ",
              "begin": "F2021",
              "end": "",
              "minUnits": 3,
              "maxUnits": 3,
              "publishedCourseIdentifierYearTermId": null,
              "position": 0,
              "type": "Course"
            }
          ]
        }
      ]
    },
    {
      "target": {
        "courseIdentifierParentId": 376639,
        "courseTitle": "Weather, Climate, and the Environment",
        "courseNumber": "015",
        "prefix": "ESS",
        "prefixParentId": 13948,
        "prefixDescription": "Environmental Systems Science",
        "departmentParentId": 13808,
        "department": "Environmental Systems Science",
        "begin": "F2019",
        "end": "",
        "minUnits": 4,
        "maxUnits": 4
      },
      "courses": [
        {
          "group": "And",
          "classes": [
            {
              "visibleCrossListedCourses": [],
              "requisites": [],
              "attributes": [],
              "courseIdentifierParentId": 144722,
              "courseTitle": "Weather and Climate",
              "courseNumber": "140 C",
              "prefix": "GEOG",
              "prefixParentId": 10555,
              "prefixDescription": "Geography",
              "departmentParentId": 6181,
              "department": "Geography",
              "begin": "F2002",
              "end": "",
              "minUnits": 3,
              "maxUnits": 3,
              "publishedCourseIdentifierYearTermId": 207,
              "position": 0,
              "type": "Course"
            }
          ]
        }
      ]
    },
    {
      "target": {
        "courseIdentifierParentId": 356651,
        "courseTitle": "Fundamentals of Geology",
        "courseNumber": "020",
        "prefix": "ESS",
        "prefixParentId": 13948,
        "prefixDescription": "Environmental Systems Science",
        "departmentParentId": 13808,
        "department": "Environmental Systems Science",
        "begin": "F2019",
        "end": "",
        "minUnits": 4,
        "maxUnits": 4
      },
      "courses": [
        {
          "group": "And",
          "classes": [
            {
              "visibleCrossListedCourses": [],
              "requisites": [],
              "attributes": [],
              "courseIdentifierParentId": 145231,
              "courseTitle": "Physical Geology",
              "courseNumber": "100 C",
              "prefix": "GEOL",
              "prefixParentId": 11288,
              "prefixDescription": "Geology",
              "departmentParentId": 6324,
              "department": "Geology",
              "begin": "F2002",
              "end": "",
              "minUnits": 3,
              "maxUnits": 3,
              "publishedCourseIdentifierYearTermId": 207,
              "position": 0,
              "type": "Course"
            }
          ]
        },
        {
          "group": "And",
          "classes": [
            {
              "visibleCrossListedCourses": [],
              "requisites": [],
              "attributes": [],
              "courseIdentifierParentId": 32995,
              "courseTitle": "Physical Geology Laboratory",
              "courseNumber": "101 C",
              "prefix": "GEOL",
              "prefixParentId": 11288,
              "prefixDescription": "Geology",
              "departmentParentId": 6324,
              "department": "Geology",
              "begin": "F2002",
              "end": "",
              "minUnits": 1,
              "maxUnits": 1,
              "publishedCourseIdentifierYearTermId": 207,
              "position": 0,
              "type": "Course"
            }
          ]
        },
        {
          "group": "And",
          "classes": [
            {
              "visibleCrossListedCourses": [],
              "requisites": [],
              "attributes": [],
              "courseIdentifierParentId": 206593,
              "courseTitle": "Honors Physical Geology",
              "courseNumber": "100HC",
              "prefix": "GEOL",
              "prefixParentId": 11288,
              "prefixDescription": "Geology",
              "departmentParentId": 6324,
              "department": "Geology",
              "begin": "F2004",
              "end": "",
              "minUnits": 3,
              "maxUnits": 3,
              "publishedCourseIdentifierYearTermId": 215,
              "position": 0,
              "type": "Course"
            }
          ]
        },
        {
          "group": "And",
          "classes": [
            {
              "visibleCrossListedCourses": [],
              "requisites": [],
              "attributes": [],
              "courseIdentifierParentId": 32995,
              "courseTitle": "Physical Geology Laboratory",
              "courseNumber": "101 C",
              "prefix": "GEOL",
              "prefixParentId": 11288,
              "prefixDescription": "Geology",
              "departmentParentId": 6324,
              "department": "Geology",
              "begin": "F2002",
              "end": "",
              "minUnits": 1,
              "maxUnits": 1,
              "publishedCourseIdentifierYearTermId": 207,
              "position": 0,
              "type": "Course"
            }
          ]
        }
      ]
    },
    {
      "target": {
        "courseIdentifierParentId": 270041,
        "courseTitle": "Introduction to Biological Anthropology",
        "courseNumber": "005",
        "prefix": "ANTH",
        "prefixParentId": 13940,
        "prefixDescription": "Anthropology",
        "departmentParentId": 769,
        "department": "Anthropology",
        "begin": "F2019",
        "end": "",
        "minUnits": 4,
        "maxUnits": 4
      },
      "courses": [
        {
          "group": "And",
          "classes": [
            {
              "visibleCrossListedCourses": [],
              "requisites": [],
              "attributes": [],
              "courseIdentifierParentId": 346500,
              "courseTitle": "Biological Anthropology",
              "courseNumber": "101 C",
              "prefix": "ANTH",
              "prefixParentId": 10752,
              "prefixDescription": "Anthropology",
              "departmentParentId": 724,
              "department": "Anthropology",
              "begin": "F2007",
              "end": "",
              "minUnits": 3,
              "maxUnits": 3,
              "publishedCourseIdentifierYearTermId": null,
              "position": 0,
              "type": "Course"
            }
          ]
        }
      ]
    },
    {
      "target": {
        "courseIdentifierParentId": 345846,
        "courseTitle": "Preparatory Chemistry",
        "courseNumber": "001",
        "prefix": "CHEM",
        "prefixParentId": 13945,
        "prefixDescription": "Chemistry",
        "departmentParentId": 2383,
        "department": "Chemistry",
        "begin": "F2019",
        "end": "",
        "minUnits": 3,
        "maxUnits": 3
      },
      "courses": [
        {
          "group": "And",
          "classes": [
            {
              "visibleCrossListedCourses": [],
              "requisites": [],
              "attributes": [],
              "courseIdentifierParentId": 299572,
              "courseTitle": "Chem for Health Sci Majors I",
              "courseNumber": "101 C",
              "prefix": "CHEM",
              "prefixParentId": 3810,
              "prefixDescription": "Chemistry",
              "departmentParentId": 2323,
              "department": "Chemistry",
              "begin": "F2020",
              "end": "",
              "minUnits": 4.5,
              "maxUnits": 4.5,
              "publishedCourseIdentifierYearTermId": null,
              "position": 0,
              "type": "Course"
            }
          ]
        },
        {
          "group": "And",
          "classes": [
            {
              "visibleCrossListedCourses": [],
              "requisites": [],
              "attributes": [],
              "courseIdentifierParentId": 279312,
              "courseTitle": "Preparation for General Chem",
              "courseNumber": "107 C",
              "prefix": "CHEM",
              "prefixParentId": 3810,
              "prefixDescription": "Chemistry",
              "departmentParentId": 2323,
              "department": "Chemistry",
              "begin": "F2013",
              "end": "",
              "minUnits": 5,
              "maxUnits": 5,
              "publishedCourseIdentifierYearTermId": null,
              "position": 0,
              "type": "Course"
            }
          ]
        }
      ]
    },
    {
      "target": {
        "courseIdentifierParentId": 380303,
        "courseTitle": "Introduction to Computing",
        "courseNumber": "019",
        "prefix": "CSE",
        "prefixParentId": 13947,
        "prefixDescription": "Computer Science and Engineering",
        "departmentParentId": 3279,
        "department": "Computer Science and Engineering",
        "begin": "F2021",
        "end": "",
        "minUnits": 4,
        "maxUnits": 4
      },
      "courses": [
        {
          "group": "And",
          "classes": [
            {
              "visibleCrossListedCourses": [],
              "requisites": [],
              "attributes": [],
              "courseIdentifierParentId": 231374,
              "courseTitle": "Java Programming",
              "courseNumber": "226 C",
              "prefix": "CIS",
              "prefixParentId": 2217,
              "prefixDescription": "Computer Information Systems",
              "departmentParentId": 3109,
              "department": "Computer Information Systems",
              "begin": "F2006",
              "end": "",
              "minUnits": 3,
              "maxUnits": 3,
              "publishedCourseIdentifierYearTermId": null,
              "position": 0,
              "type": "Course"
            }
          ]
        },
        {
          "group": "And",
          "classes": [
            {
              "visibleCrossListedCourses": [],
              "requisites": [],
              "attributes": [],
              "courseIdentifierParentId": 294756,
              "courseTitle": "Introduction to Programming Concepts in C++",
              "courseNumber": "123 C",
              "prefix": "CSCI",
              "prefixParentId": 515,
              "prefixDescription": "Computer Science",
              "departmentParentId": 3261,
              "department": "Computer Science",
              "begin": "F2020",
              "end": "",
              "minUnits": 3,
              "maxUnits": 3,
              "publishedCourseIdentifierYearTermId": null,
              "position": 0,
              "type": "Course"
            }
          ]
        },
        {
          "group": "And",
          "classes": [
            {
              "visibleCrossListedCourses": [],
              "requisites": [],
              "attributes": [],
              "courseIdentifierParentId": 241599,
              "courseTitle": "Visual/C++ Programming",
              "courseNumber": "223 C",
              "prefix": "CIS",
              "prefixParentId": 2217,
              "prefixDescription": "Computer Information Systems",
              "departmentParentId": 3109,
              "department": "Computer Information Systems",
              "begin": "F2004",
              "end": "",
              "minUnits": 3,
              "maxUnits": 3,
              "publishedCourseIdentifierYearTermId": null,
              "position": 0,
              "type": "Course"
            }
          ]
        }
      ]
    },
    {
      "target": {
        "courseIdentifierParentId": 269477,
        "courseTitle": "Statistical Inference",
        "courseNumber": "010",
        "prefix": "ECON",
        "prefixParentId": 13949,
        "prefixDescription": "Economics",
        "departmentParentId": 4341,
        "department": "Economics",
        "begin": "F2019",
        "end": "",
        "minUnits": 4,
        "maxUnits": 4
      },
      "courses": [
        {
          "group": "And",
          "classes": [
            {
              "visibleCrossListedCourses": [],
              "requisites": [],
              "attributes": [],
              "courseIdentifierParentId": 377374,
              "courseTitle": "Introduction to Probability and Statistics",
              "courseNumber": "120PC",
              "prefix": "MATH",
              "prefixParentId": 9978,
              "prefixDescription": "Mathematics",
              "departmentParentId": 9004,
              "department": "Mathematics",
              "begin": "F2021",
              "end": "",
              "minUnits": 4,
              "maxUnits": 4,
              "publishedCourseIdentifierYearTermId": 283,
              "position": 0,
              "type": "Course"
            }
          ]
        },
        {
          "group": "And",
          "classes": [
            {
              "visibleCrossListedCourses": [],
              "requisites": [],
              "attributes": [],
              "courseIdentifierParentId": 278552,
              "courseTitle": "Introduction to Probability and Statistics",
              "courseNumber": "120 C",
              "prefix": "MATH",
              "prefixParentId": 9978,
              "prefixDescription": "Mathematics",
              "departmentParentId": 9004,
              "department": "Mathematics",
              "begin": "F2016",
              "end": "",
              "minUnits": 4,
              "maxUnits": 4,
              "publishedCourseIdentifierYearTermId": 263,
              "position": 0,
              "type": "Course"
            }
          ]
        }
      ]
    }
  ],
  "groups": {
    "MAJOR PREPARATION COURSES REQUIRED FOR TRANSFER": [
      {
        "instruction": {
          "type": "Conjunction",
          "conjunction": "And",
          "id": "c4d137eb-140d-4916-bcab-08db93657755",
          "selectionType": "Complete"
        },
        "sections": [
          [
            {
              "type": "Course",
              "course": {
                "courseIdentifierParentId": 356654,
                "courseTitle": "Introduction to Economics",
                "courseNumber": "001",
                "prefix": "ECON",
                "prefixParentId": 13949,
                "prefixDescription": "Economics",
                "departmentParentId": 4341,
                "department": "Economics",
                "begin": "F2019",
                "end": "",
                "minUnits": 4,
                "maxUnits": 4
              },
              "visibleCrossListedCourses": [],
              "requisites": [],
              "courseAttributes": [],
              "id": "d438d6c4-2b7b-4c23-bd73-205aa2c45da9",
              "position": 0,
              "attributes": []
            }
          ],
          [
            {
              "type": "Course",
              "course": {
                "courseIdentifierParentId": 296244,
                "courseTitle": "Calculus II for Physical Sciences & Engineering",
                "courseNumber": "022",
                "prefix": "MATH",
                "prefixParentId": 13957,
                "prefixDescription": "Mathematics",
                "departmentParentId": 9070,
                "department": "Mathematics",
                "begin": "F2019",
                "end": "",
                "minUnits": 4,
                "maxUnits": 4
              },
              "visibleCrossListedCourses": [],
              "requisites": [],
              "courseAttributes": [],
              "id": "74a46c33-94e7-4f55-9754-e5342e909691",
              "position": 0,
              "attributes": []
            },
            {
              "type": "Course",
              "course": {
                "courseIdentifierParentId": 269482,
                "courseTitle": "Calculus I for Physical Sciences & Engineering",
                "courseNumber": "021",
                "prefix": "MATH",
                "prefixParentId": 13957,
                "prefixDescription": "Mathematics",
                "departmentParentId": 9070,
                "department": "Mathematics",
                "begin": "F2019",
                "end": "",
                "minUnits": 4,
                "maxUnits": 4
              },
              "visibleCrossListedCourses": [],
              "requisites": [],
              "courseAttributes": [],
              "id": "3bed28ee-f038-4cab-999b-66f1cac2ac54",
              "position": 0,
              "attributes": []
            }
          ]
        ]
      }
    ],
    "ADDITIONAL MAJOR PREPARATION COURSES": [
      {
        "instruction": {
          "type": "Following",
          "id": "34eb30cc-d8e2-48f2-dd3c-08db99b6efac",
          "selectionType": "Select"
        },
        "sections": [
          [
            {
              "type": "Course",
              "course": {
                "courseIdentifierParentId": 269477,
                "courseTitle": "Statistical Inference",
                "courseNumber": "010",
                "prefix": "ECON",
                "prefixParentId": 13949,
                "prefixDescription": "Economics",
                "departmentParentId": 4341,
                "department": "Economics",
                "begin": "F2019",
                "end": "",
                "minUnits": 4,
                "maxUnits": 4
              },
              "visibleCrossListedCourses": [],
              "requisites": [],
              "courseAttributes": [],
              "id": "9d0c6075-c42d-4b84-9a79-e27bdaa63ba3",
              "position": 0,
              "attributes": []
            }
          ]
        ]
      }
    ],
    "MATHEMATICS": [
      {
        "instruction": {
          "type": "Following",
          "id": "74076648-3f4f-4bff-dd44-08db99b6efac",
          "selectionType": "Select"
        },
        "sections": [
          [
            {
              "type": "Course",
              "course": {
                "courseIdentifierParentId": 299518,
                "courseTitle": "Linear Algebra and Differential Equations",
                "courseNumber": "024",
                "prefix": "MATH",
                "prefixParentId": 13957,
                "prefixDescription": "Mathematics",
                "departmentParentId": 9070,
                "department": "Mathematics",
                "begin": "F2019",
                "end": "",
                "minUnits": 4,
                "maxUnits": 4
              },
              "visibleCrossListedCourses": [],
              "requisites": [],
              "courseAttributes": [],
              "id": "b07df43b-0efe-4ff3-8cb6-d674c8029f98",
              "position": 0,
              "attributes": []
            },
            {
              "type": "Course",
              "course": {
                "courseIdentifierParentId": 299516,
                "courseTitle": "Vector Calculus",
                "courseNumber": "023",
                "prefix": "MATH",
                "prefixParentId": 13957,
                "prefixDescription": "Mathematics",
                "departmentParentId": 9070,
                "department": "Mathematics",
                "begin": "F2019",
                "end": "",
                "minUnits": 4,
                "maxUnits": 4
              },
              "visibleCrossListedCourses": [],
              "requisites": [],
              "courseAttributes": [
                {
                  "position": 0,
                  "content": "**REFER TO TOP OF AGREEMENT**"
                }
              ],
              "id": "94e36a28-2eef-45f7-86fd-156e4c856f58",
              "position": 0,
              "attributes": []
            }
          ]
        ]
      }
    ],
    "COMPUTER SCIENCE": [
      {
        "instruction": {
          "type": "NFromArea",
          "amount": 1,
          "amountQuantifier": "None",
          "amountUnitType": "Course",
          "toAmountDeterminer": "None",
          "toAmount": 1,
          "areaType": "None",
          "id": "5dd59a82-a5f4-4bb4-dd40-08db99b6efac",
          "selectionType": "Select"
        },
        "sections": [
          [
            {
              "type": "Course",
              "course": {
                "courseIdentifierParentId": 380303,
                "courseTitle": "Introduction to Computing",
                "courseNumber": "019",
                "prefix": "CSE",
                "prefixParentId": 13947,
                "prefixDescription": "Computer Science and Engineering",
                "departmentParentId": 3279,
                "department": "Computer Science and Engineering",
                "begin": "F2021",
                "end": "",
                "minUnits": 4,
                "maxUnits": 4
              },
              "visibleCrossListedCourses": [],
              "requisites": [],
              "courseAttributes": [],
              "id": "27220042-69bd-47f8-ac3d-a20ac4d90d41",
              "position": 0,
              "attributes": []
            },
            {
              "type": "Course",
              "course": {
                "courseIdentifierParentId": 363871,
                "courseTitle": "Introduction to Computing with Python",
                "courseNumber": "021",
                "prefix": "BIOE",
                "prefixParentId": 13942,
                "prefixDescription": "Bioengineering",
                "departmentParentId": 1618,
                "department": "Bioengineering",
                "begin": "F2021",
                "end": "",
                "minUnits": 4,
                "maxUnits": 4
              },
              "visibleCrossListedCourses": [],
              "requisites": [],
              "courseAttributes": [],
              "id": "6871f228-744e-43f0-ae98-e01d53cd292d",
              "position": 0,
              "attributes": []
            }
          ]
        ]
      }
    ],
    "SOCIAL SCIENCE REQUIREMENT": [
      {
        "instruction": {
          "type": "NFromArea",
          "amount": 1,
          "amountQuantifier": "None",
          "amountUnitType": "Course",
          "toAmountDeterminer": "None",
          "toAmount": 1,
          "areaType": "None",
          "id": "bb50ce96-5edc-45d7-dd45-08db99b6efac",
          "selectionType": "Select"
        },
        "sections": [
          [
            {
              "type": "Course",
              "course": {
                "courseIdentifierParentId": 299506,
                "courseTitle": "Introduction to Sociocultural Anthropology",
                "courseNumber": "001",
                "prefix": "ANTH",
                "prefixParentId": 13940,
                "prefixDescription": "Anthropology",
                "departmentParentId": 769,
                "department": "Anthropology",
                "begin": "F2019",
                "end": "",
                "minUnits": 4,
                "maxUnits": 4
              },
              "visibleCrossListedCourses": [],
              "requisites": [],
              "courseAttributes": [],
              "id": "71b7b99a-72db-4984-26b7-08db93657f9b",
              "position": 0,
              "attributes": []
            },
            {
              "type": "Course",
              "course": {
                "courseIdentifierParentId": 356648,
                "courseTitle": "Introduction to Cognitive Science",
                "courseNumber": "001",
                "prefix": "COGS",
                "prefixParentId": 13946,
                "prefixDescription": "Cognitive Science",
                "departmentParentId": 2716,
                "department": "Cognitive Science",
                "begin": "F2019",
                "end": "",
                "minUnits": 4,
                "maxUnits": 4
              },
              "visibleCrossListedCourses": [],
              "requisites": [],
              "courseAttributes": [],
              "id": "a9e1fc38-50f1-4458-26b8-08db93657f9b",
              "position": 0,
              "attributes": []
            },
            {
              "type": "Course",
              "course": {
                "courseIdentifierParentId": 273195,
                "courseTitle": "Introduction to Public Health",
                "courseNumber": "001",
                "prefix": "PH",
                "prefixParentId": 15646,
                "prefixDescription": "Public Health",
                "departmentParentId": 11343,
                "department": "Public Health",
                "begin": "F2019",
                "end": "",
                "minUnits": 4,
                "maxUnits": 4
              },
              "visibleCrossListedCourses": [],
              "requisites": [],
              "courseAttributes": [],
              "id": "f7d9c2ef-4b6f-466e-26b9-08db93657f9b",
              "position": 0,
              "attributes": []
            },
            {
              "type": "Course",
              "course": {
                "courseIdentifierParentId": 304580,
                "courseTitle": "Global and International Public Health",
                "courseNumber": "005",
                "prefix": "PH",
                "prefixParentId": 15646,
                "prefixDescription": "Public Health",
                "departmentParentId": 11343,
                "department": "Public Health",
                "begin": "F2019",
                "end": "",
                "minUnits": 4,
                "maxUnits": 4
              },
              "visibleCrossListedCourses": [],
              "requisites": [],
              "courseAttributes": [],
              "id": "21c59f71-b675-49b8-26ba-08db93657f9b",
              "position": 0,
              "attributes": []
            },
            {
              "type": "Course",
              "course": {
                "courseIdentifierParentId": 269488,
                "courseTitle": "Introduction to Psychology",
                "courseNumber": "001",
                "prefix": "PSY",
                "prefixParentId": 13961,
                "prefixDescription": "Psychology",
                "departmentParentId": 11217,
                "department": "Psychology",
                "begin": "F2019",
                "end": "",
                "minUnits": 4,
                "maxUnits": 4
              },
              "visibleCrossListedCourses": [],
              "requisites": [],
              "courseAttributes": [],
              "id": "c0ce79db-7ab1-4799-26bb-08db93657f9b",
              "position": 0,
              "attributes": []
            },
            {
              "type": "Course",
              "course": {
                "courseIdentifierParentId": 356657,
                "courseTitle": "Introduction to American Politics",
                "courseNumber": "001",
                "prefix": "POLI",
                "prefixParentId": 13960,
                "prefixDescription": "Political Science",
                "departmentParentId": 11019,
                "department": "Political Science",
                "begin": "F2019",
                "end": "",
                "minUnits": 4,
                "maxUnits": 4
              },
              "visibleCrossListedCourses": [],
              "requisites": [],
              "courseAttributes": [],
              "id": "5c5993ca-5d64-437d-26bc-08db93657f9b",
              "position": 0,
              "attributes": []
            },
            {
              "type": "Course",
              "course": {
                "courseIdentifierParentId": 299521,
                "courseTitle": "Introduction to Sociology",
                "courseNumber": "001",
                "prefix": "SOC",
                "prefixParentId": 13963,
                "prefixDescription": "Sociology",
                "departmentParentId": 12129,
                "department": "Sociology",
                "begin": "F2019",
                "end": "",
                "minUnits": 4,
                "maxUnits": 4
              },
              "visibleCrossListedCourses": [],
              "requisites": [],
              "courseAttributes": [],
              "id": "4c6183b0-d3a5-457c-26bd-08db93657f9b",
              "position": 0,
              "attributes": []
            }
          ]
        ]
      }
    ],
    "NATURAL SCIENCE": [
      {
        "instruction": null,
        "sections": [
          [
            {
              "type": "Course",
              "course": {
                "courseIdentifierParentId": 377544,
                "courseTitle": "Biodiversity and Conservation",
                "courseNumber": "043",
                "prefix": "ESS",
                "prefixParentId": 13948,
                "prefixDescription": "Environmental Systems Science",
                "departmentParentId": 13808,
                "department": "Environmental Systems Science",
                "begin": "F2019",
                "end": "",
                "minUnits": 4,
                "maxUnits": 4
              },
              "visibleCrossListedCourses": [
                {
                  "course": {
                    "courseIdentifierParentId": 357254,
                    "courseTitle": "Biodiversity and Conservation",
                    "courseNumber": "043",
                    "prefix": "BIO",
                    "prefixParentId": 13943,
                    "prefixDescription": "Biological Sciences",
                    "departmentParentId": 1651,
                    "department": "Biological Sciences",
                    "begin": "F2019",
                    "end": "",
                    "minUnits": 4,
                    "maxUnits": 4
                  }
                }
              ],
              "requisites": [],
              "courseAttributes": [],
              "id": "27915c74-361b-400c-a950-7a2a5dc63534",
              "position": 0,
              "attributes": []
            },
            {
              "type": "Course",
              "course": {
                "courseIdentifierParentId": 299509,
                "courseTitle": "Human Development",
                "courseNumber": "050",
                "prefix": "BIO",
                "prefixParentId": 13943,
                "prefixDescription": "Biological Sciences",
                "departmentParentId": 1651,
                "department": "Biological Sciences",
                "begin": "F2019",
                "end": "",
                "minUnits": 4,
                "maxUnits": 4
              },
              "visibleCrossListedCourses": [],
              "requisites": [],
              "courseAttributes": [],
              "id": "a0db6748-11b1-4744-be87-d4c0d12d8df2",
              "position": 0,
              "attributes": []
            },
            {
              "type": "Course",
              "course": {
                "courseIdentifierParentId": 356647,
                "courseTitle": "Nutrition",
                "courseNumber": "060",
                "prefix": "BIO",
                "prefixParentId": 13943,
                "prefixDescription": "Biological Sciences",
                "departmentParentId": 1651,
                "department": "Biological Sciences",
                "begin": "F2019",
                "end": "",
                "minUnits": 4,
                "maxUnits": 4
              },
              "visibleCrossListedCourses": [],
              "requisites": [],
              "courseAttributes": [],
              "id": "d09fbf4a-2597-4b5b-bad5-2e6e4be54109",
              "position": 0,
              "attributes": []
            },
            {
              "type": "Course",
              "course": {
                "courseIdentifierParentId": 376639,
                "courseTitle": "Weather, Climate, and the Environment",
                "courseNumber": "015",
                "prefix": "ESS",
                "prefixParentId": 13948,
                "prefixDescription": "Environmental Systems Science",
                "departmentParentId": 13808,
                "department": "Environmental Systems Science",
                "begin": "F2019",
                "end": "",
                "minUnits": 4,
                "maxUnits": 4
              },
              "visibleCrossListedCourses": [],
              "requisites": [],
              "courseAttributes": [],
              "id": "5440520a-b278-47d2-adf8-5bf82faa0aa8",
              "position": 0,
              "attributes": []
            },
            {
              "type": "Course",
              "course": {
                "courseIdentifierParentId": 356651,
                "courseTitle": "Fundamentals of Geology",
                "courseNumber": "020",
                "prefix": "ESS",
                "prefixParentId": 13948,
                "prefixDescription": "Environmental Systems Science",
                "departmentParentId": 13808,
                "department": "Environmental Systems Science",
                "begin": "F2019",
                "end": "",
                "minUnits": 4,
                "maxUnits": 4
              },
              "visibleCrossListedCourses": [],
              "requisites": [],
              "courseAttributes": [],
              "id": "5fca2e12-9443-49ee-9c0d-f1822f0ba96f",
              "position": 0,
              "attributes": []
            },
            {
              "type": "Course",
              "course": {
                "courseIdentifierParentId": 270041,
                "courseTitle": "Introduction to Biological Anthropology",
                "courseNumber": "005",
                "prefix": "ANTH",
                "prefixParentId": 13940,
                "prefixDescription": "Anthropology",
                "departmentParentId": 769,
                "department": "Anthropology",
                "begin": "F2019",
                "end": "",
                "minUnits": 4,
                "maxUnits": 4
              },
              "visibleCrossListedCourses": [],
              "requisites": [],
              "courseAttributes": [],
              "id": "83a4c2d9-ed73-473f-b318-e9afc7a2d5f2",
              "position": 0,
              "attributes": []
            },
            {
              "type": "Course",
              "course": {
                "courseIdentifierParentId": 301697,
                "courseTitle": "Concepts & Issues in Biology Today",
                "courseNumber": "005",
                "prefix": "BIO",
                "prefixParentId": 13943,
                "prefixDescription": "Biological Sciences",
                "departmentParentId": 1651,
                "department": "Biological Sciences",
                "begin": "F2019",
                "end": "",
                "minUnits": 4,
                "maxUnits": 4
              },
              "visibleCrossListedCourses": [],
              "requisites": [],
              "courseAttributes": [],
              "id": "c58fdbf8-de46-4154-8634-72d8939ab777",
              "position": 0,
              "attributes": []
            },
            {
              "type": "Course",
              "course": {
                "courseIdentifierParentId": 356649,
                "courseTitle": "Earth Resources and Society",
                "courseNumber": "010",
                "prefix": "ESS",
                "prefixParentId": 13948,
                "prefixDescription": "Environmental Systems Science",
                "departmentParentId": 13808,
                "department": "Environmental Systems Science",
                "begin": "F2019",
                "end": "",
                "minUnits": 4,
                "maxUnits": 4
              },
              "visibleCrossListedCourses": [],
              "requisites": [],
              "courseAttributes": [],
              "id": "a00079f0-4bf5-406d-bbd6-1cdc6a25f780",
              "position": 0,
              "attributes": []
            },
            {
              "type": "Course",
              "course": {
                "courseIdentifierParentId": 356646,
                "courseTitle": "Cancer and Aging",
                "courseNumber": "051",
                "prefix": "BIO",
                "prefixParentId": 13943,
                "prefixDescription": "Biological Sciences",
                "departmentParentId": 1651,
                "department": "Biological Sciences",
                "begin": "F2019",
                "end": "",
                "minUnits": 4,
                "maxUnits": 4
              },
              "visibleCrossListedCourses": [],
              "requisites": [],
              "courseAttributes": [],
              "id": "92e604d2-2206-4047-a0d5-ffff9b935057",
              "position": 0,
              "attributes": []
            },
            {
              "type": "Course",
              "course": {
                "courseIdentifierParentId": 345846,
                "courseTitle": "Preparatory Chemistry",
                "courseNumber": "001",
                "prefix": "CHEM",
                "prefixParentId": 13945,
                "prefixDescription": "Chemistry",
                "departmentParentId": 2383,
                "department": "Chemistry",
                "begin": "F2019",
                "end": "",
                "minUnits": 3,
                "maxUnits": 3
              },
              "visibleCrossListedCourses": [],
              "requisites": [],
              "courseAttributes": [],
              "id": "4e91ce24-c40a-4da3-916a-9df22582a736",
              "position": 0,
              "attributes": []
            },
            {
              "type": "Course",
              "course": {
                "courseIdentifierParentId": 273786,
                "courseTitle": "Astrobiology",
                "courseNumber": "047",
                "prefix": "ESS",
                "prefixParentId": 13948,
                "prefixDescription": "Environmental Systems Science",
                "departmentParentId": 13808,
                "department": "Environmental Systems Science",
                "begin": "F2019",
                "end": "",
                "minUnits": 4,
                "maxUnits": 4
              },
              "visibleCrossListedCourses": [
                {
                  "course": {
                    "courseIdentifierParentId": 273785,
                    "courseTitle": "Astrobiology",
                    "courseNumber": "047",
                    "prefix": "BIO",
                    "prefixParentId": 13943,
                    "prefixDescription": "Biological Sciences",
                    "departmentParentId": 1651,
                    "department": "Biological Sciences",
                    "begin": "F2019",
                    "end": "",
                    "minUnits": 4,
                    "maxUnits": 4
                  }
                }
              ],
              "requisites": [],
              "courseAttributes": [],
              "id": "f877a3e7-15ca-4f36-892b-9f941da4471d",
              "position": 0,
              "attributes": []
            },
            {
              "type": "Course",
              "course": {
                "courseIdentifierParentId": 357826,
                "courseTitle": "Natural History of Dinosaurs",
                "courseNumber": "065",
                "prefix": "ESS",
                "prefixParentId": 13948,
                "prefixDescription": "Environmental Systems Science",
                "departmentParentId": 13808,
                "department": "Environmental Systems Science",
                "begin": "F2019",
                "end": "",
                "minUnits": 4,
                "maxUnits": 4
              },
              "visibleCrossListedCourses": [
                {
                  "course": {
                    "courseIdentifierParentId": 273791,
                    "courseTitle": "Natural History of Dinosaurs",
                    "courseNumber": "065",
                    "prefix": "BIO",
                    "prefixParentId": 13943,
                    "prefixDescription": "Biological Sciences",
                    "departmentParentId": 1651,
                    "department": "Biological Sciences",
                    "begin": "F2019",
                    "end": "",
                    "minUnits": 4,
                    "maxUnits": 4
                  }
                }
              ],
              "requisites": [],
              "courseAttributes": [],
              "id": "64d175fc-cab6-4e5c-9e3c-58e4f4fd7dd9",
              "position": 0,
              "attributes": []
            },
            {
              "type": "Course",
              "course": {
                "courseIdentifierParentId": 301710,
                "courseTitle": "Sustainability Science",
                "courseNumber": "002",
                "prefix": "ESS",
                "prefixParentId": 13948,
                "prefixDescription": "Environmental Systems Science",
                "departmentParentId": 13808,
                "department": "Environmental Systems Science",
                "begin": "F2019",
                "end": "",
                "minUnits": 4,
                "maxUnits": 4
              },
              "visibleCrossListedCourses": [],
              "requisites": [],
              "courseAttributes": [],
              "id": "241e5594-7e16-4491-bd85-8f4ec0542522",
              "position": 0,
              "attributes": []
            },
            {
              "type": "Course",
              "course": {
                "courseIdentifierParentId": 269471,
                "courseTitle": "To Know Ourselves: Molecular Basis of Health and Disease",
                "courseNumber": "003",
                "prefix": "BIO",
                "prefixParentId": 13943,
                "prefixDescription": "Biological Sciences",
                "departmentParentId": 1651,
                "department": "Biological Sciences",
                "begin": "F2019",
                "end": "",
                "minUnits": 4,
                "maxUnits": 4
              },
              "visibleCrossListedCourses": [],
              "requisites": [],
              "courseAttributes": [],
              "id": "903430b5-2e74-48ff-ab89-822c51140432",
              "position": 0,
              "attributes": []
            },
            {
              "type": "Course",
              "course": {
                "courseIdentifierParentId": 296237,
                "courseTitle": "Introduction to Earth Systems Science",
                "courseNumber": "001",
                "prefix": "ESS",
                "prefixParentId": 13948,
                "prefixDescription": "Environmental Systems Science",
                "departmentParentId": 13808,
                "department": "Environmental Systems Science",
                "begin": "F2019",
                "end": "",
                "minUnits": 4,
                "maxUnits": 4
              },
              "visibleCrossListedCourses": [],
              "requisites": [],
              "courseAttributes": [],
              "id": "f45fc6f2-dd02-4e30-9575-aedfbd212b3e",
              "position": 0,
              "attributes": []
            },
            {
              "type": "Course",
              "course": {
                "courseIdentifierParentId": 296239,
                "courseTitle": "Ecosystems of California",
                "courseNumber": "050",
                "prefix": "ESS",
                "prefixParentId": 13948,
                "prefixDescription": "Environmental Systems Science",
                "departmentParentId": 13808,
                "department": "Environmental Systems Science",
                "begin": "F2019",
                "end": "",
                "minUnits": 4,
                "maxUnits": 4
              },
              "visibleCrossListedCourses": [],
              "requisites": [],
              "courseAttributes": [],
              "id": "92891d5b-2a48-4fcf-857f-3ed52d6ab839",
              "position": 0,
              "attributes": []
            }
          ]
        ]
      }
    ],
    "ENGLISH COMPOSITION": [
      {
        "instruction": {
          "type": "Following",
          "id": "2a3b5ca8-9997-4fe3-dd46-08db99b6efac",
          "selectionType": "Complete"
        },
        "sections": [
          [
            {
              "type": "Course",
              "course": {
                "courseIdentifierParentId": 269491,
                "courseTitle": "Academic Writing",
                "courseNumber": "001",
                "prefix": "WRI",
                "prefixParentId": 13965,
                "prefixDescription": "Writing",
                "departmentParentId": 13255,
                "department": "Writing",
                "begin": "F2019",
                "end": "",
                "minUnits": 4,
                "maxUnits": 4
              },
              "visibleCrossListedCourses": [],
              "requisites": [],
              "courseAttributes": [
                {
                  "position": 0,
                  "content": "**REFER TO TOP OF AGREEMENT**"
                },
                {
                  "position": 1,
                  "content": "Minimum grade required: C or better"
                }
              ],
              "id": "ad2e2f23-0fc3-4aea-26be-08db93657f9b",
              "position": 0,
              "attributes": []
            }
          ]
        ]
      }
    ],
    "SECOND COURSE IN ENGLISH COMPOSITION": [
      {
        "instruction": {
          "type": "Following",
          "id": "b71d4d98-6004-4dc8-dd43-08db99b6efac",
          "selectionType": "Complete"
        },
        "sections": [
          [
            {
              "type": "Course",
              "course": {
                "courseIdentifierParentId": 296253,
                "courseTitle": "College Reading and Composition",
                "courseNumber": "010",
                "prefix": "WRI",
                "prefixParentId": 13965,
                "prefixDescription": "Writing",
                "departmentParentId": 13255,
                "department": "Writing",
                "begin": "F2019",
                "end": "",
                "minUnits": 4,
                "maxUnits": 4
              },
              "visibleCrossListedCourses": [],
              "requisites": [],
              "courseAttributes": [
                {
                  "position": 0,
                  "content": "**REFER TO TOP OF AGREEMENT**"
                },
                {
                  "position": 1,
                  "content": "Minimum grade required: C or better"
                }
              ],
              "id": "0048f053-6adc-4cf9-26bf-08db93657f9b",
              "position": 0,
              "attributes": []
            }
          ]
        ]
      }
    ]
  }
}